Workbook

Sheet Start here
A1: SLAM build spec
A2: Tab | B2: What it is | C2: Use it for
A3: Start here | B3: This page | C3: What each tab is and the order to read them
A4: Roadmap | B4: Phases 1 to 8 | C4: Where we are (phase 2) and what each later phase holds
A5: Feature list | B5: Every feature, tagged | C5: Core, Standard, Only SLAM, all 9 YMOYL steps, books/blogs/podcasts, next-level ideas; who each comes from, its time view and phase
A6: Visualizations | B6: Every chart | C6: What each chart looks like, what it reads, where it lives, and its time view
A7: Build phases | B7: How phase 3 gets built | C7: 12 build steps in dependency order, each with 'done when'
A8: QA checklist | B8: How you'll check each phase | C8: What you click and what you should see before saying 'next'
A9: Look and feel | B9: Colors, type, spacing, formats | C9: Exact values so nothing is left to taste. Proposed values marked
A10: Words and states | B10: Tone, empty states, errors | C10: What each screen says before anything is entered, and every confirmation
A11: Navigation | B11: Where everything lives | C11: Site map, one home for every thing, click paths for common tasks
A12: DMMT check | B12: Don't Make Me Think audit | C12: Each Krug principle, how it's applied, what was fixed, what to watch
A13: Screens | B13: The 8 screens | C13: Purpose, when used, who sees it
... A25: Open questions | B25: Still to decide | C25: Answer in the yellow column

Sheet Roadmap
A1: Roadmap: we're in phase 2
A2: Phase | B2: Name | C2: Status | D2: What's in it | E2: Done means
A3: 1 | B3: Experiments | C3: Done | D3: Money Rooms v1 to v3, SPARKS, SLAM in Personalfinance | E3: Learned what works; left baggage
A4: 2 | B4: The spec | C4: Now | D4: This workbook: every field, rule, formula, screen and feature | E4: One source of truth, nothing built from old code
A5: 3 | B5: Rebuild the core | C5: Next | D5: Build phases 0 to 11: records, math, staples, navigation, My Money, Spending, Plan, Report, Home, coach tools, dry run. All Core, Standard and 'Now' items | E5: Ready to run a live session 1 with a client
A6: 4 | B6: Coaching depth | C6: Later | D6: YMOYL exercises, joy per dollar, What Matters, mistake tracker, graceful degradation, small wins, Pareto, statement upload (CSV and PDF), canon checks (Baby Steps, Conscious Spending, PAW/UAW) | E6: Every monthly money date has something new to look at
A7: 5 | B7: The future, in depth | C7: Later | D7: True FI, decumulation, Roth ladder, 72(t), rule of 55, ACA, Social Security, life simulator, scenarios, Die With Zero, geo arbitrage, house hack, side income tools | E7: One plan from now through retirement
A8: 6 | B8: Clients in the app | C8: Later | D8: Phone-first client view, client logging between sessions, comments, pre-call link, monthly money date, next-level features | E8: Clients use it between sessions
A9: 7 | B9: Delight and community | C9: Later | D9: Wrapped, advice translator, shareable milestones, peer comparison, community money date | E9: People share it
A10: 8 | B10: Connect | C10: Someday | D10: Bank connection, paystub and 1040 readers | E10: Less typing

Sheet Feature list
A1: Every feature, tagged by tier, person, source and phase
A2: Tier | B2: Feature | C2: What it does | D2: Inspired by (people) | E2: Source | F2: Time view | G2: Phase | H2: In spec? | I2: Your comments
A3: CORE: a budgeting app built from scratch
A4: Core | B4: Records for every money item | C4: One record type behind bills, paychecks, debts, accounts | E4: Every budgeting app | F4: Every record can show its hours | G4: 3 | H4: Yes
A5: Core | B5: Budget with five passes | C5: Gut, Basics, Rough, Estimate, Actual | D5: Eli | E5: SLAM | F5: Each line in hours of work | G5: 3 | H5: Yes
A6: Core | B6: Cash flow calendar | C6: Day-by-day in and out with a running balance | E6: Every budgeting app | F6: Hours worked to cover each bill | G6: 3 | H6: Yes
A7: Core | B7: Net worth, liquid and total | C7: Assets minus debts, two ways | E7: Every planning app | F7: Net worth as months of freedom | G7: 3 | H7: Yes
A8: Core | B8: Debt payoff dates and interest | C8: Months, date, total interest per debt | E8: Every debt app | F8: Interest as hours of work | G8: 3 | H8: Yes
A9: Core | B9: Savings rate | C9: Take-home headline, gross in Show the math | D9: Mr. Money Mustache | E9: MMM blog | F9: Days of freedom bought per month | G9: 3 | H9: Yes
A10: Core | B10: Month-end close | C10: Actuals vs estimates, misses, carry adjustments | E10: YNAB-style apps | G10: 3 | H10: Yes
A11: Core | B11: Export, import, undo, autosave | C11: Never lose work | G11: 3 | H11: Yes
A12: STANDARD: what the well-known apps have
A13: Standard | B13: FI number and FI date | C13: Spending / withdrawal rate, then a monthly projection | D13: Trinity Study authors; Mindy Jensen, Scott Trench | E13: Trinity Study; BiggerPockets Money | F13: Countdown in months | G13: 3 | H13: Yes
A14: Standard | B14: FI milestones (Lean, Coast, Barista, Regular, Fat) | C14: Dated or condition-based milestones | D14: FIRE community | E14: r/financialindependence, ProjectionLab | F14: Months to each | G14: 3 | H14: Yes
A15: Standard | B15: Avalanche and snowball payoff | C15: Order and simulated payoff with extra payments | D15: Dave Ramsey (snowball) | E15: The Total Money Makeover | F15: Months saved | G15: 3 | H15: Yes
A16: Standard | B16: Cash flow Sankey | C16: Income to spending to saving | E16: ProjectionLab, Monarch | F16: Hours per branch | G16: 3 | H16: Yes
A17: Standard | B17: Category charts | C17: Where the money went | E17: YNAB, Monarch, Rocket Money | F17: Hours per category | G17: 3 | H17: Yes
A18: Standard | B18: Recurring bills list | C18: Every repeating charge and date | E18: Rocket Money | F18: Hours per year per subscription | G18: 3 | H18: Yes
A19: Standard | B19: Couples in one household | C19: Owner on every row, joint | E19: Monarch | G19: 3 | H19: Yes
A20: Standard | B20: Tax estimate | C20: Federal plus FICA | E20: Boldin | F20: Hours worked for taxes | G20: 3 | H20: Yes
A21: Standard | B21: Contribution limit tracking | C21: How much of each limit is used | E21: Boldin, Empower | G21: 3 | H21: Yes
A22: Standard | B22: Give every dollar a job | C22: Zero-based plan: income minus planned = $0 | D22: Jesse Mecham | E22: YNAB | G22: 4 | H22: Backlog
A23: Standard | B23: Sinking funds | C23: Save monthly for known yearly costs | E23: YNAB, budgeting community | F23: Hours per month set aside | G23: 3 | H23: Yes (irregular costs)
A24: Standard | B24: Statement upload (CSV and PDF) | C24: Lines matched to records, duplicates flagged | E24: Most apps | G24: 4 | H24: Backlog
A25: ONLY SLAM: ideas nobody else has
A26: Only SLAM | B26: These are big deals | C26: FI date under every return, inflation and withdrawal preset; names the biggest mover | D26: Eli | E26: SLAM | F26: Years of work each assumption adds | G26: 3 | H26: Yes
A27: Only SLAM | B27: Money as time, everywhere | C27: One toggle: dollars, hours of work, or FI days, on every number | D27: Vicki Robin, Joe Dominguez; Grant Sabatier | E27: Your Money or Your Life; Financial Freedom | F27: This is the time view | G27: 3 | H27: Yes
A28: Only SLAM | B28: Stress-weighted payoff | C28: Order debts by how much they weigh on you, with the extra interest shown | D28: Eli | E28: SLAM | F28: Hours of extra work for peace of mind | G28: 3 | H28: Yes
A29: Only SLAM | B29: Gut accuracy score | C29: How far the client's own guesses were from actual, over time | D29: Eli | E29: SLAM | G29: 3 | H29: Yes
A30: Only SLAM | B30: Amount and timing grid | C30: Fixed/variable amount x fixed/variable date; different move for each | D30: Eli | E30: SLAM | G30: 3 | H30: Yes
A31: Only SLAM | B31: Rule of 5 | C31: Age / 5 months of savings with the exact monthly add | D31: Eli | E31: SLAM | F31: Months of freedom held | G31: 3 | H31: Yes
A32: Only SLAM | B32: Support received | C32: How much others cover and what happens if it stops | D32: Eli | E32: SLAM | F32: Hours others work for you | G32: 3 | H32: Yes
A33: Only SLAM | B33: Maybe money | C33: Expected income kept out of the balance until it lands | D33: Eli; Lindsey Swanson, Jessica Goedtel (irregular income planning) | E33: Sex-worker financial planning | G33: 3 | H33: Yes
A34: Only SLAM | B34: Wins on the calendar | C34: Payoffs, milestones, raises as dated chips | D34: Eli | E34: SLAM | G34: 3 | H34: Yes
A35: Only SLAM | B35: Show the math | C35: Click any computed number to see its formula filled in with the client's numbers | D35: Eli | E35: SLAM | G35: 3 | H35: Yes
A36: Only SLAM | B36: Change since last session | C36: ▲ ▼ differences under key numbers | D36: Eli | E36: SLAM | G36: 3 | H36: Yes
A37: Only SLAM | B37: Live-call keyboard flow | C37: Tab, Enter for a new row, / for Find, Ctrl+Z | D37: Eli | E37: SLAM | G37: 3 | H37: Yes
A38: Only SLAM | B38: Benefit finder | C38: Unused employer benefits and their value | D38: Eli | E38: SLAM | F38: Hours of pay left on the table | G38: 3 | H38: Yes
A39: Only SLAM | B39: Materiality by your hourly wage | C39: Hides anything worth less than your time | D39: Eli (audit thinking) | E39: SLAM | F39: Built on the time view | G39: 3 | H39: Yes
A40: Only SLAM | B40: Solvers | C40: What would have to be true to hit FI by an age; payment to beat a promo | D40: Eli | E40: SLAM | G40: 3 | H40: Yes
A41: Only SLAM | B41: Bonus paycheck months | C41: Flags 3-paycheck months and where that money goes | D41: Eli | E41: SLAM | G41: 3 | H41: Yes
A42: Only SLAM | B42: Mistake cost tracker | C42: Unavoidable vs mistake; long-term cost and repeats | D42: Eli | E42: SLAM | F42: Hours each mistake cost | G42: 4 | H42: Backlog
A43: Only SLAM | B43: Joy per dollar | C43: Happiness per line, share of joy, joy per dollar | D43: Eli; Ramit Sethi (rich life) | E43: SLAM; I Will Teach You to Be Rich | F43: Joy per hour of work | G43: 4 | H43: Backlog
A44: Only SLAM | B44: What Matters | C44: Ranked priorities with spending tagged to each | D44: Eli; Alex Hormozi (values episode) | E44: SLAM | F44: Hours per priority | G44: 4 | H44: Backlog
A45: Only SLAM | B45: Graceful degradation | C45: Months at full, DRAFTT, FAT, food and housing only | D45: Eli | E45: SLAM | F45: Months at each level | G45: 4 | H45: Backlog
A46: Only SLAM | B46: Zombie apocalypse runway | C46: Your runway vs peers, as a fun scare | D46: Eli | E46: SLAM | F46: Days you'd last | G46: 4 | H46: Backlog
A47: Only SLAM | B47: Small wins mini-games | C47: Batch $100-a-year fixes into quick games | D47: Eli; Brad Barrett (quick wins) | E47: SLAM; ChooseFI | F47: Hours saved per win | G47: 4 | H47: Backlog
A48: Only SLAM | B48: Life Pyramid lens | C48: Maslow pyramid as a bar chart of spending | D48: Eli | E48: SLAM | G48: 4 | H48: Backlog
A49: Only SLAM | B49: Pareto of spending | C49: The few transactions making most of the spending | D49: Eli | E49: SLAM | G49: 4 | H49: Backlog
A50: Only SLAM | B50: True FI (after tax) | C50: FI number after withdrawal taxes, a dramatic unlock | D50: Eli; Jeremy Jacobson (0% tax) | E50: SLAM; Go Curry Cracker | F50: Months gained or lost | G50: 5 | H50: Backlog
A51: Only SLAM | B51: Life simulator | C51: Drag life events into order, watch FI move | D51: Eli | E51: SLAM | F51: Years each event costs | G51: 5 | H51: Backlog
A52: Only SLAM | B52: Go-go, slow-go, no-go | C52: Retirement spending by phase | D52: Eli; Bill Perkins | E52: SLAM; Die With Zero | G52: 5 | H52: Backlog
A53: Only SLAM | B53: Advice translator | C53: What applies to you now, before, and what to unlearn | D53: Eli | E53: SLAM | G53: 7 | H53: Backlog
A54: Only SLAM | B54: Wrapped | C54: Spotify-style year in review | D54: Eli | E54: SLAM | F54: Hours saved this year | G54: 7 | H54: Backlog
A55: YOUR MONEY OR YOUR LIFE: all nine steps
A56: YMOYL | B56: Step 1a: Lifetime earnings | C56: Add up every dollar earned since your first job | D56: Vicki Robin, Joe Dominguez | E56: Your Money or Your Life, step 1 | F56: Total hours of life traded | G56: 4 | H56: No
A57: YMOYL | B57: Step 1b: What do I have to show for it | C57: Personal balance sheet of everything you own | D57: Vicki Robin, Joe Dominguez | E57: YMOYL step 1 | G57: 3 | H57: Partly (net worth)
A58: YMOYL | B58: Step 2a: Real hourly wage (life energy) | C58: Take-home minus work costs, divided by all job hours including commute and recovery | D58: Vicki Robin, Joe Dominguez | E58: YMOYL step 2 | F58: The base of every time view | G58: 3 | H58: Yes
A59: YMOYL | B59: Step 2b: Track every cent | C59: Log every dollar in and out | D59: Vicki Robin, Joe Dominguez | E59: YMOYL step 2 | G59: 3 | H59: Yes (calendar)
A60: YMOYL | B60: Step 3: Monthly tabulation in life energy | C60: Monthly categories converted into hours of life | D60: Vicki Robin, Joe Dominguez | E60: YMOYL step 3 | F60: Every category in hours | G60: 3 | H60: Partly
A61: YMOYL | B61: Step 4: The three questions | C61: Per category: fulfillment? aligned with values? would it change without a job? Mark +, -, 0 | D61: Vicki Robin, Joe Dominguez | E61: YMOYL step 4 | G61: 4 | H61: No
A62: YMOYL | B62: Step 5: Wall chart | C62: Monthly income and spending lines over years | D62: Vicki Robin, Joe Dominguez | E62: YMOYL step 5 | G62: 4 | H62: No
A63: YMOYL | B63: Step 6: Lower spending | C63: Ideas for each minus category, tied to the three questions | D63: Vicki Robin, Joe Dominguez | E63: YMOYL step 6 | F63: Hours freed | G63: 4 | H63: No
A64: YMOYL | B64: Step 7: Raise income | C64: Value your life energy; income ideas by hour | D64: Vicki Robin, Joe Dominguez | E64: YMOYL step 7 | G64: 4 | H64: No
A65: YMOYL | B65: Step 8: Crossover point | C65: Monthly investment income line meets monthly spending line | D65: Vicki Robin, Joe Dominguez | E65: YMOYL step 8 | G65: 4 | H65: No
A66: YMOYL | B66: Step 9: Managing your finances | C66: Steady safe income from capital | D66: Vicki Robin, Joe Dominguez | E66: YMOYL step 9 | G66: 5 | H66: No
A67: YMOYL | B67: Fulfillment curve and 'enough' | C67: Where each category sits on the curve: survival, comforts, luxuries, enough | D67: Vicki Robin, Joe Dominguez | E67: YMOYL | G67: 4 | H67: No
A68: FROM THE BOOKS, BLOGS AND PODCASTS
A69: Canon | B69: Shockingly Simple Math | C69: Savings rate to years to FI, on your own numbers | D69: Mr. Money Mustache | E69: MMM blog | F69: Years to FI | G69: 3 | H69: Partly (built before)
A70: Canon | B70: Car and commute cost check | C70: True cost of a car and a long commute | D70: Mr. Money Mustache | E70: MMM blog | F70: Hours per year driving and paying | G70: 4 | H70: No
A71: Canon | B71: F-You money meter | C71: Months you could walk away from a job | D71: JL Collins | E71: The Simple Path to Wealth | F71: Months of freedom | G71: 3 | H71: Partly (runway)
A72: Canon | B72: Accumulate vs preserve stage | C72: Which stage you're in and the matching mix | D72: JL Collins | E72: The Simple Path to Wealth | G72: 5 | H72: No
A73: Canon | B73: Three-fund portfolio check | C73: Allocation vs a simple three-fund mix | D73: Taylor Larimore | E73: The Bogleheads' Guide to the Three-Fund Portfolio | G73: 5 | H73: No
A74: Canon | B74: Time buckets | C74: Plan experiences by life stage | D74: Bill Perkins | E74: Die With Zero | G74: 5 | H74: No
A75: Canon | B75: Memory dividends | C75: Experiences valued by the memories they pay back | D75: Bill Perkins | E75: Die With Zero | G75: 5 | H75: No (old calculator idea)
A76: Canon | B76: Net worth peak | C76: When spending down should start | D76: Bill Perkins | E76: Die With Zero | G76: 5 | H76: No
A77: Canon | B77: Enough and room for error | C77: Your 'enough' number and your margin of safety | D77: Morgan Housel | E77: The Psychology of Money | G77: 4 | H77: No
A78: Canon | B78: Conscious Spending Plan | C78: Fixed costs, investments, savings, guilt-free buckets vs their ranges | D78: Ramit Sethi | E78: I Will Teach You to Be Rich | G78: 4 | H78: No
A79: Canon | B79: Money Dials | C79: The few things you love spending on | D79: Ramit Sethi | E79: I Will Teach You to Be Rich | G79: 4 | H79: No
A80: Canon | B80: Automation map | C80: Which accounts move money on which day | D80: Ramit Sethi; David Bach | E80: IWT; The Automatic Millionaire | G80: 4 | H80: No
A81: Canon | B81: Latte factor | C81: Small repeating spends grown to their future value | D81: David Bach | E81: The Automatic Millionaire | F81: Hours per latte | G81: 4 | H81: Partly (variable lines)
A82: Canon | B82: Expected net worth (PAW/UAW) | C82: Age x pretax income / 10 vs actual net worth | D82: Thomas Stanley, William Danko | E82: The Millionaire Next Door | G82: 4 | H82: No
A83: Canon | B83: Assets vs liabilities by cash flow | C83: Does it put money in or take it out each month | D83: Robert Kiyosaki | E83: Rich Dad Poor Dad | G83: 4 | H83: No
A84: Canon | B84: Cashflow quadrant | C84: Income by employee, self-employed, business, investor | D84: Robert Kiyosaki | E84: Cashflow Quadrant | G84: 4 | H84: No
A85: Canon | B85: Baby Steps tracker | C85: Which of the 7 steps you're on | D85: Dave Ramsey | E85: The Total Money Makeover | G85: 4 | H85: No
A86: Canon | B86: Financial Order of Operations | C86: Which of the 9 steps you're on and the next dollar | D86: Brian Preston, Bo Hanson | E86: The Money Guy Show | G86: 3 | H86: Partly (built before)
A87: Canon | B87: Wealth multiplier | C87: What $1 saved today becomes at retirement, by age | D87: Brian Preston, Bo Hanson | E87: The Money Guy Show | F87: Hours today vs dollars later | G87: 4 | H87: No
A88: Canon | B88: 20/3/8 car rule | C88: Car purchase check: 20% down, 3 years, under 8% of income | D88: Brian Preston, Bo Hanson | E88: The Money Guy Show | G88: 4 | H88: No
A89: Canon | B89: Dreamlining | C89: Dreams with costs and a target monthly income | D89: Tim Ferriss | E89: The 4-Hour Workweek | F89: Months of work per dream | G89: 5 | H89: No
A90: Canon | B90: Mini-retirement planner | C90: Sabbaticals priced and placed on the timeline | D90: Tim Ferriss | E90: The 4-Hour Workweek | G90: 5 | H90: Backlog (scenario)
A91: Canon | B91: Wealth stages ($25k, $100k) | C91: Which stage and the moves that matter there | D91: Scott Trench | E91: Set for Life | G91: 4 | H91: No
A92: Canon | B92: House hack calculator | C92: Living-cost offset from renting part of your home | D92: Scott Trench | E92: Set for Life; BiggerPockets | F92: Hours of rent saved | G92: 5 | H92: Backlog
A93: Canon | B93: Yield shield and cash cushion | C93: Drawdown buffers for bad markets | D93: Kristy Shen, Bryce Leung | E93: Quit Like a Millionaire | G93: 5 | H93: No
A94: Canon | B94: Geographic arbitrage | C94: Same life, different city or country, with taxes and healthcare | D94: Kristy Shen, Bryce Leung | E94: Quit Like a Millionaire | F94: Years of FI gained | G94: 5 | H94: Backlog (scenario)
A95: Canon | B95: Safe withdrawal and sequence risk | C95: Failure risk of your withdrawal rate in bad sequences | D95: Karsten Jeske (Big ERN) | E95: Early Retirement Now | G95: 5 | H95: No
A96: Canon | B96: Roth conversion ladder | C96: Year-by-year conversions to reach retirement money early | D96: Brandon (Mad Fientist) | E96: Mad Fientist | G96: 5 | H96: Backlog
A97: Canon | B97: HSA as a retirement account | C97: Invest the HSA and save receipts | D97: Brandon (Mad Fientist) | E97: Mad Fientist | G97: 5 | H97: No
A98: Canon | B98: 0% tax early retirement | C98: Income shaped to pay little or no tax | D98: Jeremy Jacobson | E98: Go Curry Cracker | G98: 5 | H98: Backlog (True FI)
A99: Canon | B99: Travel rewards value | C99: Points earned from normal spending, valued in trips | D99: Brad Barrett | E99: ChooseFI | G99: 5 | H99: Backlog (card library)
A100: Canon | B100: Afford anything, not everything | C100: Every choice shows what it costs elsewhere | D100: Paula Pant | E100: Afford Anything | F100: Hours of other goals given up | G100: 4 | H100: No
...

Sheet Visualizations
A1: Every chart and what it looks like
A2: Chart | B2: Type | C2: What you see | D2: Reads | E2: Where it lives | F2: Interaction | G2: Time view
A3: Net worth donuts | B3: Rings | C3: Big ring for net worth split by account type; smaller rings for assets, liabilities, equity; tabs underneath open each list | D3: Accounts, debts | E3: Report > Overview | F3: Hover shows the item; click jumps to its home | G3: Months of freedom in the center
A4: Net worth over time | B4: Line | C4: One line per snapshot date; dots where sessions happened; dashed line for liquid net worth | D4: Snapshots, history | E4: Report > History | F4: Drag to zoom a range | G4: Months of freedom on the second axis
A5: Cash flow Sankey | B5: Sankey | C5: Income on the left flows into taxes, needs, wants, debt, saving on the right; width = dollars | D5: Income, spending lines | E5: Report > Overview | F5: Click a branch to filter the budget | G5: Branch width in hours
A6: Gross to take-home | B6: Waterfall | C6: Gross bar steps down through federal, FICA, pretax deductions to take-home | D6: Income, Math M10-M12 | E6: My Money > Income | F6: Hover shows each amount | G6: Hours of each workday spent on each
A7: DRAFTT shares | B7: 100% bar | C7: One horizontal bar split into Debt, Retirement, Accommodation, Food, Transportation, (Taxes, Therapy) | D7: Spending lines | E7: My Money visuals panel, Report | F7: Click a letter to see its lines | G7: Hours per letter
A8: Amount and timing grid | B8: 2x2 bubbles | C8: Four boxes (fixed/variable amount x fixed/variable date); bubble size = dollars; bottom-right box shaded as risk | D8: Spending lines | E8: Spending > Budget | F8: Click a box to filter | G8: Bubble labels in hours
A9: Estimate vs actual | B9: Bullet bars | C9: Per line: grey estimate bar, solid actual bar, a tick for Gut | D9: Budget passes | E9: Spending > Month-end close | F9: Sort by biggest miss | G9: Misses in hours
A10: Gut accuracy over time | B10: Line | C10: Average % off per month falling over time | D10: History | E10: Report > History
A11: Running balance | B11: Line under the calendar | C11: Thin line of end-of-day balance with the low balance line dashed; maybe money as a dotted band | D11: Calendar entries | E11: Spending > Cash flow calendar | F11: Hover a day | G11: Days of runway
A12: Debt payoff | B12: Stacked area | C12: Each debt's balance shrinking to zero; flags at each payoff date | D12: Debts, Math M34 | E12: Plan > Debt payoff | F12: Extra payment slider moves the flags | G12: Interest in hours
A13: Payoff order compare | B13: Grouped bars | C13: Avalanche vs snowball vs stress: months and total interest side by side | D13: Math M34 | E13: Plan > Debt payoff | G13: Hours of interest
A14: FI timeline | B14: Line with fan | C14: Invested balance rising to the FI line; pessimistic to optimistic band; milestone flags | D14: Math M53 | E14: Plan > Timeline | F14: Savings slider moves the date | G14: Years of work left
A15: These are big deals | B15: Tornado | C15: One bar per assumption showing how far it moves the FI date; biggest on top | D15: Math M56 | E15: Plan > Goals | F15: Click a bar to set that preset | G15: Years per assumption
A16: Milestone ladder | B16: Steps | C16: Lean, Coast, Barista, Regular, Fat FI as stairs, each filled by % | D16: Math M55 | E16: Plan > Goals | G16: Months to each step
A17: Savings rate to years | B17: Curve | C17: MMM's curve of savings rate vs years to FI with your dot on it | D17: Math | E17: Plan > Timeline | F17: Drag your dot | G17: This is in years
A18: Crossover point | B18: Two lines | C18: Monthly investment income rising to meet monthly spending (YMOYL wall chart) | D18: Math | E18: Plan > Timeline
A19: Fulfillment curve | B19: Curve | C19: Survival, comforts, luxuries, enough; each category placed on it | D19: Three questions | E19: Spending (phase 4)
A20: Rule of 5 gauge | B20: Gauge | C20: Emergency cash vs age/5 months target; keep-pace add shown under it | D20: Math M43 | E20: My Money > Assets, Home | G20: Months held
A21: Graceful degradation | B21: Staircase | C21: Months at full spending, DRAFTT, FAT, food and housing only | D21: Math | E21: Report (phase 4) | G21: Months at each step
A22: Joy per dollar | B22: Scatter | C22: Cost on x, happiness on y; top-left = cheap joy, bottom-right = expensive and joyless | D22: Happiness ratings | E22: Spending (phase 4) | F22: Click a dot to open the line | G22: Cost in hours
A23: Pareto | B23: Bars plus line | C23: Biggest spends as bars with the cumulative % line | D23: Calendar actuals | E23: Report (phase 4) | G23: Hours per spend
A24: Life Pyramid | B24: Pyramid bars | C24: Maslow levels as bars showing spending at each | D24: Spending lines | E24: Report (phase 4)
A25: Support received | B25: Stacked bar | C25: Your share vs others' share for each covered line | D25: Who pays | E25: Report > Overview | G25: Hours others cover
A26: Contribution limits | B26: Progress bars | C26: Each account's year-to-date vs its limit | D26: Reference data | E26: My Money > Assets
A27: Expected net worth | B27: Gauge | C27: Actual net worth vs age x income / 10 | D27: PAW/UAW formula | E27: Report (phase 4)
A28: Money as time chips | B28: Inline chips | C28: Small grey chip next to any amount: '14 hrs' or '3 FI days' | D28: Real hourly wage | E28: Everywhere | F28: Global toggle | G28: This is the time view
A29: Wrapped | B29: Story cards | C29: Swipeable cards: biggest win, debt paid, accuracy, top categories, hours saved | D29: History | E29: Report (phase 7) | G29: Hours saved this year

Sheet Build phases
A1: Build phases, in dependency order
A2: Phase | B2: Name | C2: What gets built | D2: Done when
A3: 0 | B3: Setup | C3: New repo, /spec from this workbook (one CSV per tab), test runner, .gitignore for fixtures/*.local.json | D3: Repo runs locally; spec files exist; Test client is NOT in git
A4: 1 | B4: Records and storage | C4: One record type, dated history on every change, autosave, undo/redo, snapshots, export/import | D4: Unit tests: add, edit, delete, undo, history, export → import round-trips
A5: 2 | B5: Math engine | C5: Every Math tab formula as a pure function with tests | D5: All Test client expected values match within $1 or 1 month
A6: 3 | B6: Staples | C6: All Staples tab pieces on one demo page | D6: Each staple works on the demo page; affordances pass (buttons look like buttons)
A7: 4 | B7: Shell and navigation | C7: Top bar (left, middle, right), 5 tabs, sub-tabs, breadcrumb, Find, quick add, parking lot, client view, gear | D7: Trunk test passes on every empty screen
A8: 5 | B8: My Money | C8: Profile with gates hub, Income, Debt, Assets, Protection, Taxes; Fast Track mode; One page toggle; visuals panel | D8: Your test client can be entered start to finish; gates add and remove sections
A9: 6 | B9: Spending | C9: Budget with five passes, fixed/variable and timing tags, who pays, bulk select, link to card, irregular costs; calendar; month-end close | D9: A full month can be planned, logged and closed for the test client
A10: 7 | B10: Plan | C10: Goals with presets, big-deals card, milestones, timeline, debt payoff, next 12 months, solvers | D10: FI dates match the Test client expected values
A11: 8 | B11: Report | C11: Overview (donuts, metrics shelf, Sankey), one-pager, history | D11: Every number links to its home
A12: 9 | B12: Home | C12: Prep, Live, Wrap-up with one main button each | D12: A mock session runs from Start session to Send summary
A13: 10 | B13: Coach tools and discovery | C13: Revisit list, homework, snapshots, export, reset, notes, discovery table, new client | D13: New client from discovery opens Home in Prep
A14: 11 | B14: Dry run | C14: Full fake session 1 end to end; screenshots; QUESTIONS.md | D14: You do one real run-through and log every 'where do I put this'

Sheet QA checklist
A1: How you'll check each phase
A2: Build phase | B2: Name | C2: What you do | D2: What you should see
A3: 0 | B3: Setup | C3: Open the repo on GitHub | D3: spec/csv has one file per tab; .gitignore lists fixtures/*.local.json; no real numbers anywhere
A4: 1 | B4: Records | C4: Run the tests (Claude Code reports them); open the staples page later | D4: Add, edit, delete, undo, history and export/import tests pass
A5: 2 | B5: Math | C5: Read the report's match table | D5: Every Demo client and Test client expected value matches within $1 or 1 month
A6: 3 | B6: Staples | C6: Open the staples demo page | D6: Every staple from the Staples tab is there; it looks like the approved preview page; every box in a row lines up; time toggle changes amounts
A7: 4 | B7: Shell | C7: Click every tab and sub-tab; drop yourself on a random screen | D7: Trunk test: site, client, page, sections, search all visible; nothing says $0; empty states read like the Words tab
A8: 5 | B8: My Money | C8: Enter your own numbers with Fast Track, then in full | D8: Under 5 minutes for Fast Track; gates add and remove sections; car loan shows on Assets and Debt
A9: 6 | B9: Spending | C9: Plan, log and close one month | D9: Calendar balance matches the budget; Partial and Maybe behave; bulk select links bills to a card in 3 clicks
A10: 7 | B10: Plan | C10: Change presets on the big-deals card | D10: FI date matches the expected values; tornado names the biggest mover
A11: 8 | B11: Report | C11: Click every number | D11: Each number opens its home
A12: 9 | B12: Home | C12: Run Start session to Send summary | D12: One main button per moment; wrap-up does all four steps
A13: 10 | B13: Coach tools | C13: Create a client from discovery | D13: Opens Home in Prep with the discovery numbers marked Roughly
A14: 11 | B14: Dry run | C14: A full fake session 1 | D14: Your 'where do I put this' list is empty, or becomes the next prompt

Sheet Look and feel
A1: Look and feel (proposed values marked)
A2: Item | B2: Value | C2: Used for | D2: Status
A3: COLORS (from the preview, Oct 28, version 3)
A4: Modes | B4: Light and dark, both designed. Follows the computer's setting, with a Light | Dark switch in settings | D4: Decided (your feedback)
A5: Page background | B5: Light: #E4E9F2 soft blue-grey (not bright white). Dark: #0E1729 | D5: Decided (your feedback)
A6: Cards and rows | B6: Light: #F2F5FA. Dark: #16223D | D6: Decided
A7: Text | B7: Light: #060E1F, weight 500. Dark: #F4F7FC | C7: High contrast | D7: Decided (your feedback)
A8: Secondary text | B8: Light: #26344F. Dark: #CBD6EA | D8: Decided
A9: Primary (sapphire) | B9: Light: #1747A6. Dark: #7AA6F5 with dark text on it | C9: Main buttons, current tab and sub-tab | D9: Decided
A10: Primary dark | B10: Light: #0A2A66. Dark: #06142F | C10: Top bar, warnings | D10: Decided
A11: Primary light | B11: Light: #9FB9EA. Dark: #2C4A85 | C11: Selected rows (deeper than before) | D11: Decided (your feedback)
A12: Computed fill | B12: Light: #CBD6EA. Dark: #24365C | C12: Can't be typed in; text stays dark/light | D12: Decided
A13: Borders | B13: Light: #4E6694 on inputs and buttons, #A9B9D6 row lines. Dark: #8AA2CF and #344A75 | D13: Decided
A14: Small icon buttons | B14: 32px, 2px dark outline, bold 17px icon. Top bar: solid white with navy icon | C14: Undo, duplicate, reset, delete must be easy to spot | D14: Decided (your feedback)
A15: Area hues | B15: Income green #0B7A43 · Debt plum #8E2C8F · Assets teal #0E6670 · Taxes indigo #4338CA · Needs sapphire #1747A6 · Goals rose #B0397A (lighter versions in dark mode) | C15: Sub-tab dots, section titles, charts | D15: Decided (your 'other hues')
A16: Status: Roughly | B16: Solid teal pill, white text | D16: Decided
A17: Status: Guess | B17: Solid purple pill, white text | D17: Decided
A18: Warnings | B18: Solid navy pill, white text. No yellow, orange or red anywhere | D18: Decided
A19: Good | B19: #0B7A43 | C19: Wins, done | D19: Decided
A20: TYPE AND SIZE
A21: Font | B21: Inter (Google Fonts), fallback system sans-serif; IBM Plex Sans and Source Sans 3 tried as options | C21: One font everywhere | D21: Proposed (pick one in the preview)
A22: Sizes | B22: Body 16px weight 500 · labels 14px weight 600 · section titles 18px · page titles 24px · big numbers 32px | C22: Bigger and more solid than the first proposal | D22: Decided (your feedback)
A23: Numbers | B23: Tabular figures so columns of dollars line up | D23: Decided
A24: SHAPE AND SPACE
A25: Corners | B25: 8px on cards and inputs, 6px on buttons, full round on tags | D25: Decided
A26: Spacing | B26: 4px grid: 4, 8, 12, 16, 24, 32 | D26: Decided
A27: Row height | B27: Comfortable 44px (default) or Compact 36px; 34px inputs; every box in a row sits on the same center line | C27: Your 'fields level with one another' | D27: Decided (your feedback)
A28: Chips next to inputs | B28: Sit beside the input on the same line, never above or below it | D28: Decided (your feedback)
A29: Inputs | B29: Filled: 1.5px #8FA2C6 border. Empty: 2px #4E6694 border with a hint like Add APR. Focused: 2px sapphire | C29: Visible borders rule; empty boxes stand out | D29: Decided (v4)
A30: Buttons | B30: Main: filled sapphire, white text. Secondary: white with sapphire border. Icon: 28px square. Max one main button per area | D30: Decided
A31: Row actions | B31: Duplicate, reset, delete as 32px line icons with tooltips, then one 'More ▸' text button. No ⋯ menu | C31: Your 'three dots and caret' note | D31: Decided (your feedback)
A32: Icons | B32: Line icons, 2.25 stroke, 18px, Lucide style (inline SVG or Lucide pinned from unpkg). Never emoji | D32: Decided (v4)
A33: Reference page | B33: spec/SLAM Look Preview.html (version 4) shows every value on this tab in use, light and dark | C33: Match it | D33: Decided (v4)
A34: Current sub-tab | B34: Filled sapphire with white text | D34: Decided
A35: Hover | B35: Lift 1px with a soft shadow; pointer cursor on everything clickable, nothing else | D35: Decided
A36: Screen size | B36: Laptop first: designed at 1440px, must work down to 1280px. Phone layout is phase 6 | D36: Decided
A37: Charts | B37: Apache ECharts from a CDN, using the area hues | C37: One chart library so every chart looks related | D37: Decided
A38: FORMATS
A39: Money | B39: $1,240 in summaries (no cents); $15.99 in entry fields; negative as −$240, never red | D39: Decided
A40: Percent | B40: One decimal: 22.4% | D40: Decided
A41: Dates | B41: Nov 12, 2026; months as Nov 2026 | D41: Decided
A42: Durations | B42: 26 months (Jan 2029); never rounded to years | D42: Decided
A43: Time view | B43: 14 hrs · 3 FI days | D43: Decided
A44: Empty | B44: A dash or 'Add …', never $0 | D44: Decided

Sheet Words and states
A1: Words, empty states, errors
A2: Situation | B2: What it says | C2: Notes | D2: Status
A3: THE ONE RULE
A4: Every word on screen | B4: Understood in one glance. Short, plain, obvious. If a label needs explaining, change the label | C4: Don't Make Me Think | D4: Decided (Oct 28)
A5: EMPTY STATES (first time a screen is opened)
A6: Home (no client) | B6: 'Start with a new client' + one main button | D6: Proposed
A7: My Money tab, nothing entered | B7: 'Start Fast Track' as the one main button, with 'about 5 minutes' under it | D7: Proposed
A8: A list with no rows | B8: 'No credit cards yet' + '+ Add credit card' | D8: Proposed
A9: A chart missing inputs | B9: Grey outline of the chart + 'Needs rent and take-home' with links to both | D9: Proposed
A10: A metric missing inputs | B10: 'Locked: needs 2 numbers' with links | D10: Decided
A11: Calendar, nothing planned | B11: 'Add your paychecks and bills to see your month' | D11: Proposed
A12: CONFIRMATIONS AND ERRORS
A13: After delete | B13: 'Deleted. Undo' toast, 10 seconds | D13: Decided
A14: Before reset section | B14: 'Clear all 6 debts? You can undo this.' Buttons: 'Clear debts' and 'Keep them' | D14: Proposed
A15: Save failed | B15: 'Not saved yet. Your last change is safe in this tab; export now to be sure.' + Export button | D15: Proposed
A16: Payment too small | B16: 'This payment never pays it off. It needs at least $417 a month.' | D16: Proposed
A17: Backup reminder | B17: 'Last backup 9 days ago.' + 'Back up now' | D17: Proposed
A18: SAMPLE TEXT IN THE MOCKUP
A19: Names and amounts in the Mockup tab | B19: Examples only (Maya R., $1,240, Nov 12). Never hard-code them; real values come from the client's records | D19: Decided

Sheet Navigation
A1: Navigation: where everything lives
A2: Tab or task | B2: Sub-tab or path | C2: What lives here / clicks | D2: Links and notes
A3: THE IDEA
A4: Five tabs, five jobs | B4: Home = this session. My Money = facts about today. Spending = this month. Plan = the future. Report = the report (read only) | D4: If you can't tell which tab something belongs in, ask: is it about now, this month, the future, or a summary?
A5: One home per thing | B5: Every field is entered in exactly one place. Other screens show it as a link back to its home | D5: No more 'Needs in My Money and Spending'
A6: Tabs are places, buttons are actions | B6: Start Fast Track, Start session and One page are modes, so they're buttons or toggles, not tabs
A7: Same spot, every screen | B7: Top bar: left = where am I, middle = 5 tabs, right = 8 tools. Sub-tabs always directly under the main tabs
A8: SITE MAP
A9: Home | B9: Prep | Live | Wrap-up | C9: Session notes, agenda, homework status | D9: Money in one line links to Report, Spending and Plan
A10: My Money | B10: Profile | C10: Why now, gates hub (what applies to me), about you, work and home, accounts, couples split | D10: Gates hub links to every gated section
A11: My Money | B11: Income | C11: Paychecks, benefits, variable income, equity pay | D11: Take-home total feeds Spending and Report
A12: My Money | B12: Debt | C12: Every debt row, credit score, payoff order | D12: Car loan and mortgage also show on Assets (same record)
A13: My Money | B13: Assets | C13: Cash, investments, car, home, other | D13: Net worths show on Report
A14: My Money | B14: Protection | C14: Insurance coverage and gaps | D14: Gaps become to-dos
A15: My Money | B15: Taxes | C15: Filing status, last year, estimates | D15: Rates show on Report
A16: Spending | B16: Budget | C16: Every spending line, the five passes, fixed/variable, who pays, irregular costs | D16: Lines appear on the calendar
A17: Spending | B17: Cash flow calendar | C17: Calendar entries, maybe money, wins, low balance line | D17: Card due dates come from Debt
A18: Spending | B18: Month-end close | C18: Close, misses, carry adjustments | D18: Actuals feed Report > History
A19: Plan | B19: Goals | C19: FI target, assumptions, milestones | D19: FI date shows on Home
A20: Plan | B20: Timeline | C20: FI timeline with sliders and pace bands
A21: Plan | B21: Debt payoff | C21: Payoff chart and extra payment slider | D21: Reads Debt
A22: Plan | B22: Next 12 months | C22: Upcoming events | D22: Each lands on the calendar
A23: Plan | B23: Scenarios | C23: Life event blocks (later)
A24: Report | B24: Overview | C24: Net worth donuts, metrics unlocked, Sankey | D24: Read only; every number links to its home
A25: Report | B25: One-pager | C25: Session summary, send summary
A26: Report | B26: History | C26: Snapshots over time, Wrapped later
A27: ⚙ Coach tools | B27: Lists, Data, Session | C27: Revisit list, homework, snapshots, export/import, reset, private and shared notes, settings, pre-call link | D27: Never shown in client view
A28: + New client | B28: Discovery table | C28: Creates the client from the sales call | D28: Then opens Home in Prep
A29: HOW DO I...? (clicks from anywhere)
A30: Add a credit card | B30: My Money › Debt › + Add debt › Credit card | C30: 3 clicks, or 1 with + Add anything
A31: Say the client got a car | B31: My Money › Profile › gates hub › Car ✓ | C31: 3 clicks; jumps to the new car rows
A32: Log a paycheck that arrived | B32: Spending › Cash flow calendar › chip › Got it | C32: 3 clicks
A33: Mark a bill as partly paid | B33: Spending › Cash flow calendar › chip › Partial | C33: 3 clicks
A34: Link a bill to a card | B34: More ▸ › Paid with › card name | C34: 3 clicks from the bill | D34: Or check several bills and use Link to card in the bulk bar
A35: Close the month | B35: Spending › Month-end close › Review › Close month | C35: 3 clicks
A36: See the FI date | B36: Home (it's on Money in one line) | C36: 0-1 clicks
A37: Find the HSA | B37: 🔍 Find › type 'HSA' | C37: 1 click
A38: Jot something the client said | B38: 📝 | C38: 1 click
A39: Run Fast Track | B39: My Money › Start Fast Track | C39: 2 clicks
A40: Share my screen safely | B40: Client view toggle | C40: 1 click
A41: Undo a delete | B41: Undo toast, or ↶ | C41: 1 click
A42: Send the summary | B42: Home (Wrap-up) › End session › Send summary | C42: 2-3 clicks
A43: Switch client | B43: Client name in the top bar | C43: 2 clicks

Sheet DMMT check
A1: Don't Make Me Think check
A2: Principle or check | B2: How it's applied | C2: Where | D2: Status | E2: Your comments
A3: TRUNK TEST (Krug: drop someone on any screen; can they answer these?)
A4: What site is this? | B4: 'SLAM' site ID top left on every screen | C4: All screens | D4: Applied
A5: Whose file is this? | B5: Client name next to the site ID | C5: All screens | D5: Applied
A6: What page am I on? | B6: Breadcrumb after the client name, current tab underlined, current sub-tab filled | C6: All screens | D6: Applied
A7: What are the major sections? | B7: Five main tabs, same order everywhere | C7: All screens | D7: Applied
A8: What are my options here? | B8: Sub-tabs right under the tabs; one main (filled blue) button per area | C8: All screens | D8: Applied
A9: How do I search? | B9: 🔍 Find in the same spot on every screen | C9: All screens | D9: Applied
A10: KRUG PRINCIPLES
A11: Obvious what's clickable | B11: Buttons look like buttons, fields have borders, tabs are filled, computed numbers are grey and can't be typed in | C11: Staples | D11: Applied
A12: One main action per area | B12: Each area gets at most one filled blue button (Start session, Next step, End session, + Add). Everything else is outlined or an icon | C12: Home, every section | D12: Fixed today
A13: Don't make them hunt | B13: One home per thing; Find and quick add reach any field in 1 click | C13: Navigation | D13: Fixed today
A14: Omit needless words | B14: Labels are 1-3 words; explanations go in tooltips; copy from the user's side | C14: All copy | D14: Applied
A15: Reduce noise | B15: Status tags only show when a number isn't 'Know it'. Secondary and Tertiary collapsed. Completion is one slim bar on Home | C15: All rows, Home | D15: Fixed today
A16: Conventions over cleverness | B16: Standard patterns: tabs, breadcrumb, undo toast, trash can, caret | C16: Staples | D16: Applied
A17: Mindless choices | B17: Top 4 then Other; defaults filled; 'not sure' fills a guess instead of blocking | C17: Pickers, defaults | D17: Applied
A18: Visual hierarchy | B18: Bigger = more important: #1 next number is a big card, #2 and #3 small. Money in one line has exactly 4 numbers | C18: Home | D18: Fixed today
A19: WHAT WAS FIXED TODAY
A20: Needs lived in two places | B20: My Money had a Needs tab that linked to Spending. Removed; Spending > Budget is Needs' one home | C20: My Money, Spending | D20: Fixed today
A21: Goals lived in two places | B21: Goals were a My Money tab and also on Plan. Moved to Plan > Goals; My Money is only facts about today | C21: My Money, Plan | D21: Fixed today
A22: Fast Track was a tab | B22: It's a mode that walks across tabs, so it's now a 'Start Fast Track' button | C22: My Money | D22: Fixed today
A23: Express form was a separate button | B23: Now a 'By section | One page' toggle on My Money | C23: My Money | D23: Fixed today
A24: Home tried to do everything | B24: Home now has three moments (Prep, Live, Wrap-up) that switch on their own; each shows only what that moment needs and one main button | C24: Home | D24: Fixed today
A25: 'Why are you here' sat on Home | B25: Moved to My Money > Profile > Why now (its one home); the Live agenda's step 1 links to it | C25: Home, Profile | D25: Fixed today
A26: Gates were scattered | B26: Gates hub in Profile; hidden areas show a slim '+ Add [area]' link | C26: Profile | D26: Fixed today
A27: Top bar had 11 loose items | B27: Grouped into left (where am I), middle (5 tabs), right (8 tools) | C27: All screens | D27: Fixed today
A28: WATCH
A29: Two tabs sounded alike | B29: My Money and Report renamed to My Money (enter facts about today) and Report (read the summary) | C29: Main tabs | D29: Fixed today
A30: Paid with was 4 clicks deep | B30: Now 3 clicks via More ▸, or 1 action for many bills via bulk select. The ⋯ menu was removed so there is one way in | C30: Budget | D30: Fixed today
A31: Visuals panel next to forms | B31: Charts beside inputs can crowd the screen; default to Side on wide screens, Below on narrow, Hide is one click | C31: My Money | D31: Watch
A32: Client view | B32: Make sure nothing private leaks into charts or the one-pager | C32: All screens | D32: Watch

Sheet Screens
A1: Screen | B1: Sub-tabs | C1: Purpose | D1: When it's used | E1: Who sees it | F1: Your comments
A2: Home | B2: Prep, Live, Wrap-up (switch on their own) | C2: The session cockpit: where the client is, what we're doing today, the one next thing | D2: Every call | E2: You and client
A3: My Money | B3: Profile, Income, Debt, Assets, Protection, Taxes | C3: Facts about today. Fast Track and One page are modes on top of these tabs | D3: Session 1 and updates | E3: You and client
A4: Spending | B4: Budget, Cash flow calendar, Month-end close | C4: This month: the five passes, the calendar, the close | D4: Session 1 and monthly | E4: You and client
A5: Plan | B5: Goals, Timeline, Debt payoff, Next 12 months, Scenarios | C5: The future: what you're aiming for and what moves it | D5: End of call reveal, check-ins | E5: You and client
A6: Report | B6: Overview, One-pager, History | C6: The report: read-only views of everything above | D6: End of call, monthly | E6: You and client
A7: Discovery (sales call) | C7: Quick table that creates the client and fills the map | D7: Sales call | E7: You only
A8: Pre-call form (client) | C8: Same questions as Profile, tap-only, for the client. Later phase | D8: Before session 1 | E8: Client
A9: Coach tools (⚙) | B9: Lists, Data, Session | C9: Revisit list, homework, snapshots, export, reset, notes, settings | D9: Before and after calls | E9: You only

Sheet Mockup
A1: SLAM screen mockup: each cell is one thing on screen, left to right
A2: How to read it: each item has Primary, Secondary and Tertiary layers. Under each layer, row 1 is what it looks like, row 2 is what kind of thing it is, row 3 is what it does. Move or edit cells freely; put comments in the last column.
A3: Legend | B3: Field: Type a value | C3: Picker: Type a little, pick from a list | D3: Dropdown: Pick one from a short list | E3: Toggle: Two or three choices side by side | F3: Stepper: Minus and plus to set a count | G3: Button: Does something when clicked | H3: Icon button: Small button (duplicate, delete, reset) | I3: Caret: Opens or closes the next layer | J3: Status tag: Know it / Roughly / Not sure / Will email / Not now / Not for me | K3: Computed: App works it out, never typed | L3: Label: Text only, not clickable | M3: Tab: Switches the screen or sub-screen | N3: Chart: Visual | O3: Card: A box holding a few lines or a link
A5: Screen › Section › Item | B5: Layer | C5: Row | D5: 1 | E5: 2 | F5: 3 | G5: 4 | H5: 5 | I5: 6 | J5: 7 | K5: 8 | L5: 9 | M5: 10 | N5: 11 | O5: Your comments
A6: ALL SCREENS
A7: Top bar › Left: where am I | O7: Trunk test: site, client, page and section always visible here
B8: Primary | C8: Looks like | D8: SLAM | E8: Maya R. ▾ | F8: My Money › Debt | G8: Saved ✓
C9: Type | D9: Label | E9: Picker | F9: Label | G9: Computed
C10: What it does | D10: Site ID: Stress Less About Money. Click = Home | E10: Current client; click to switch or '+ New client' | F10: Breadcrumb after the client name; each part clickable | G10: Autosaves every change; 'Unsaved' warning before closing
A12: Top bar › Middle: main tabs | O12: One job per tab. Current tab is underlined and filled
B13: Primary | C13: Looks like | D13: Home | E13: My Money | F13: Spending | G13: Plan | H13: Report
C14: Type | D14: Tab | E14: Tab | F14: Tab | G14: Tab | H14: Tab
C15: What it does | D15: This session: before, during, after | E15: Facts about today | F15: This month: budget, calendar, close | G15: The future: goals, timeline, events | H15: The report: net worth, metrics, one-pager
A17: Top bar › Right: tools | O17: Same 8 tools, same order, every screen
B18: Primary | C18: Looks like | D18: 🔍 Find | E18: + Add anything | F18: 📝 | G18: ↶ | H18: ↷ | I18: $ | Hours | FI days | J18: Client view | K18: ⚙
C19: Type | D19: Field | E19: Field | F19: Icon button | G19: Icon button | H19: Icon button | I19: Toggle | J19: Toggle | K19: Icon button
C20: What it does | D20: Type any field ('HSA') and jump to it | E20: Quick add: 'Netflix 15.99 monthly' | F20: Parking lot: quick note, always one click away | G20: Undo | H20: Redo | I20: Every number converts to time | J20: Screen-share mode: hides coach-only items, bigger text | K20: Coach tools
A22: HOME
A23: Purpose › What Home is for | O23: Home is the session cockpit. Data entry lives in My Money and Spending; reports live in Report
B24: Primary | C24: Looks like | D24: Answers 3 questions in 5 seconds | E24: Changes by moment
C25: Type | D25: Label | E25: Label
C26: What it does | D26: 1. Where is this client now? 2. What are we doing today? 3. What's the one next thing? | E26: Before the call = Prep. During = Live. After = Wrap-up. Switches on its own when you press Start session / End session
A28: Every mode › Client strip
B29: Primary | C29: Looks like | D29: Maya R. | E29: Session 2 of 6 | F29: Next: Nov 12 | G29: Active ▾ | H29: Prep | Live | Wrap-up
C30: Type | D30: Label | E30: Computed | F30: Picker | G30: Dropdown | H30: Tab
C31: What it does | E31: Package tracking | G31: Active, maintenance, paused | H31: Current moment; switches itself, can be clicked
A33: Every mode › Money in one line | O33: Exactly 4 numbers. Everything else is in Report
B34: Primary | C34: Looks like | D34: “You keep $1,240 a month and are on track for FI at 47.” | E34: Net worth | F34: Monthly surplus | G34: Savings rate | H34: FI date
C35: Type | D35: Computed | E35: Computed | F35: Computed | G35: Computed | H35: Computed
C36: What it does | D36: One plain sentence | E36: Click = Report | F36: Click = Spending | G36: Click = Report | H36: Click = Plan
B37: Secondary | C37: Looks like | D37: Since last session ▲
C38: Type | D38: Computed
C39: What it does | D39: Small arrows on each number
A41: Prep (before the call) › Prep
B42: Primary | C42: Looks like | D42: What changed since last time | E42: Open homework: 3 | F42: Due for a check: 4 | G42: Parking lot notes: 2 | H42: Start session
C43: Type | D43: Card | E43: Card | F43: Card | G43: Card | H43: Button
C44: What it does | D44: Net worth, debts paid, new numbers | E44: Click opens the list | F44: Rough or aged numbers | G44: Unfiled notes from last time | H44: The one main button. Switches Home to Live and turns on Guide me
B45: Secondary | C45: Looks like | D45: Edit today's agenda
C46: Type | D46: Button
C47: What it does | D47: Reorder or add steps
A49: Live (during the call) › Agenda
B50: Primary | C50: Looks like | D50: 1. Why now ✓ | E50: 2. Debt and cash | F50: 3. Spending basics | G50: 4. FI reveal | H50: Next step › | I50: 22 min left
C51: Type | D51: Card | E51: Card | F51: Card | G51: Card | H51: Button | I51: Computed
C52: What it does | D52: Done steps get a check; click jumps to Profile > Why now | E52: Current step, highlighted | H52: The one main button: jumps to the next field to ask | I52: From session length
A54: Live (during the call) › Next 3 numbers
B55: Primary | C55: Looks like | D55: #1 Credit card APR | E55: [ % ] | F55: #2 Rent | G55: #3 401(k) balance
C56: Type | D56: Card | E56: Field | F56: Card | G56: Card
C57: What it does | D57: Biggest effect on FI date; big card | E57: Fill right here | F57: Small | G57: Small
A59: Wrap-up (after the call) › Wrap-up checklist
B60: Primary | C60: Looks like | D60: ☐ Homework set (3) | E60: ☐ Snapshot saved | F60: ☐ One-pager ready | G60: ☐ Next session booked | H60: End session
C61: Type | D61: Card | E61: Card | F61: Card | G61: Card | H61: Button
C62: What it does | D62: From fields marked Will email | E62: Freezes today's numbers | F62: Opens Report > One-pager | H62: The one main button: does all four, then shows Send summary
B63: Secondary | C63: Looks like | D63: Send summary | E63: Money feeling 1-10
C64: Type | D64: Button | E64: Stepper
C65: What it does | D65: Email-ready one-pager plus homework | E65: Asked at the end of each session
A67: Every mode › Completion (collapsed) | O67: Was a full block before; now one slim bar so Home stays calm
B68: Primary | C68: Looks like | D68: Picture filled in: 64% | E68: ▸ By section
C69: Type | D69: Computed | E69: Caret
C70: What it does | D70: One slim bar; click to open | E70: Shows the two bars per section
B71: Secondary | C71: Looks like | D71: Profile, Income, Debt, Assets, Spending, Plan
C72: Type | D72: Chart
C73: What it does | D73: Core and full-detail bars, each with 'What's next ›'
A75: MY MONEY
A76: Sub-tabs › Sub-tab bar | O76: Needs moved to Spending (its one home). Goals moved to Plan. Fast Track is a button, not a tab
B77: Primary | C77: Looks like | D77: Profile | E77: Income | F77: Debt | G77: Assets | H77: Protection | I77: Taxes | J77: Start Fast Track | K77: By section | One page
C78: Type | D78: Tab | E78: Tab | F78: Tab | G78: Tab | H78: Tab | I78: Tab | J78: Button | K78: Toggle
C79: What it does | D79: Who they are, what applies | H79: Insurance basics | J79: A mode, not a page: walks the Basics pass across all tabs in about 5 minutes | K79: One page = the Express form
B80: Secondary | C80: Looks like | D80: Section done: 6 of 9 core
C81: Type | D81: Computed
C82: What it does | D82: Completion for this sub-tab
A84: Sub-tabs › Visuals panel | O84: Your comment: this should have lots of data visualizations and options
B85: Primary | C85: Looks like | D85: Chart for this sub-tab | E85: Chart ▾ | F85: Hide | Side | Below
C86: Type | D86: Chart | E86: Dropdown | F86: Toggle
C87: What it does | D87: Debt: balance by debt and payoff chart. Assets: allocation and liquidity tiers. Income: gross-to-take-home waterfall. Needs: DRAFTT bar. Updates live as you type | E87: Pick another chart for this sub-tab | F87: Where the panel sits; collapsed on small screens
B88: Secondary | C88: Looks like | D88: Money as time | E88: Compare: last session
C89: Type | D89: Toggle | E89: Toggle
C90: What it does | D90: Show amounts as hours worked or FI days | E90: Overlay the previous snapshot
A92: Profile › Why now
B93: Primary | C93: Looks like | D93: What prompted this call | E93: Biggest worry | F93: Goal in their words
C94: Type | D94: Field | E94: Field | F94: Field
C95: What it does | D95: Client's words; feeds the one-pager
A97: Profile › What applies to me (gates hub)
B98: Primary | C98: Looks like | D98: Car ✓ | E98: Kids ✗ | F98: Pets ✗ | G98: Rent | Own | Family | H98: Work ▾ | I98: HSA-eligible ✗ | J98: Equity pay ✗ | K98: Couple ✗
C99: Type | D99: Toggle | E99: Toggle | F99: Toggle | G99: Toggle | H99: Dropdown | I99: Toggle | J99: Toggle | K99: Toggle
C100: What it does | D100: Each gate in one place; changing one adds or removes those sections and jumps there
A102: Profile › About you
B103: Primary | C103: Looks like | D103: First name | E103: Last name | F103: Birth month/year | G103: State ▾ | H103: Solo | Couple | I103: More ▸
C104: Type | D104: Field | E104: Field | F104: Picker | G104: Picker | H104: Toggle | I104: Caret
C105: What it does | D105: F001 | E105: F002 | F105: Computes age | G105: Tax rules | H105: Couple adds Owner on every row | I105: Shows Secondary fields. Collapsed by default. Paid with sits at the top of it
B106: Secondary | C106: Looks like | D106: Partner name | E106: Partner birth month/year | F106: Dependents | G106: Health coverage ▾
C107: Type | D107: Field | E107: Picker | F107: Stepper | G107: Dropdown
C108: What it does | D108: Couples only | E108: Couples only | F108: Opens an age box per child | G108: Employer, ACA, parent's plan, Medicaid, none
A110: Profile › Work and home
B111: Primary | C111: Looks like | D111: Work situation ▾ | E111: Housing: Rent | Own | Family | F111: More ▸
C112: Type | D112: Dropdown | E112: Toggle | F112: Caret
C113: What it does | D113: Situation gate: fields that don't apply disappear | E113: Gates housing rows and home asset | F113: Shows Secondary fields. Collapsed by default. Paid with sits at the top of it
B114: Secondary | C114: Looks like | D114: Roommates | E114: Worst case: all on me | F114: Income stability: Steady | Varies | Unpredictable
C115: Type | D115: Stepper | E115: Toggle | F115: Toggle
C116: What it does | D116: Splits housing cost | E116: Recalculates with no roommate share | F116: Adjusts Rule of 5 target
A118: Profile › Accounts gate | O118: Your comment: cash, investment and real assets each get multiselects
...

Sheet Staples
A1: Staple | B1: What it looks like | C1: Where it's used | D1: Your comments
A2: Add button | B2: '+ Add [thing]', outlined, bottom left of every section | C2: Income, Debt, Assets, Needs, Protection, Goals, calendar, events
A3: Add picker | B3: Top 4 big buttons, Other with search, Name your own | C3: Every Add button
A4: Row | B4: Type/name, amount, per, owner, status, ⧉ ↺ 🗑, ▸ More | C4: Every multi-item list
A5: Caret | B5: ▸ More / ▾ Less, opens Secondary then Tertiary | C5: Every row
A6: Status tag | B6: Know it, Roughly, Not sure (Guess), Will email, Not now, Not for me, Computed | C6: Every field and row
A7: Amount box | B7: $ value with 'per' picker (paycheck, week, month, year) | C7: Every money field
A8: Who pays | B8: Me, split, included in rent, covered by someone, N/A, my share | C8: Every Needs line
A9: Paid with | B9: Checking, savings, or a card | C9: Every bill (Tertiary)
A10: Amount: Fixed | Variable | B10: Toggle with a default by category | C10: Every spending line
A11: Timing: Fixed date | Variable date | B11: Toggle with a default by category | C11: Every spending line and calendar entry
A12: Section footer | B12: Total, count, completion bar | C12: Every section
A13: Visuals panel | B13: Chart for this section with a chart picker | C13: Every My Money sub-tab
... A26: Quick add | B26: '+ Add anything' text box in the top bar | C26: All screens

Sheet Rules
A1: SLAM rules: when X, then Y, otherwise Z
A2: Source = Decided (you said it, with when or where) or Proposed (my default; confirm, change or delete). Proposed rows are shaded yellow.
A3: ID | B3: Build status | C3: Rule type | D3: Applies to | E3: When | F3: Then | G3: Otherwise | H3: Example | I3: Source | J3: Your comments | K3: Build phase
A4: R001 | B4: Not started | C4: Gate (show only if) | D4: Accounts gate | E4: An area (cash, investments, real assets, debt) is unchecked | F4: That area's sub-tab, rows, totals and charts don't appear anywhere | G4: Area appears with the rows created by the counts | I4: Decided (Sept: absent, not hidden) | K4: 5
A5: R002 | B5: Not started | C5: Gate (show only if) | D5: Accounts gate | E5: 'None of these' is checked | F5: All four areas count as complete; net worth uses zeros | I5: Decided (Sept 23: every question has an 'I don't') | K5: 5
A6: R003 | B6: Not started | C6: Gate (show only if) | D6: Accounts gate | E6: A type is picked with a count of N | F6: N blank rows of that type are created | I6: Decided (Oct 28: count first, then rows) | K6: 5
A7: R004 | B7: Not started | C7: Gate (show only if) | D7: Work situation | E7: Between jobs, student or retired | F7: Employer match, 401(k) %, paycheck deductions, vesting and equity pay don't appear | G7: They appear for employed or mixed | I7: Decided (Sept: situation gate) | K7: 5
A8: R005 | B8: Not started | C8: Gate (show only if) | D8: Work situation | E8: Self-employed or mixed | F8: Variable income block, tax set-aside %, quarterly estimates and business expenses appear | G8: Hidden | I8: Decided (accepted Oct 28; was proposed) | K8: 5
A9: R006 | B9: Not started | C9: Gate (show only if) | D9: Work situation | E9: Between jobs | F9: Unemployment benefits and runway months appear on Income and Home | G9: Hidden | I9: Decided (accepted Oct 28; was proposed) | K9: 5
A10: R007 | B10: Not started | C10: Gate (show only if) | D10: Household | E10: Solo | F10: No Owner dropdowns, no partner rows, no couples split | G10: Couple: Owner on every row, partner fields, couples split block | I10: Decided (couples support Oct 27) | K10: 5
A11: R008 | B11: Not started | C11: Gate (show only if) | D11: Housing | E11: Rent | F11: Rent line, renters insurance line | G11: Own: mortgage on home asset, property tax, insurance, HOA. Family: housing line defaults to 'covered by someone' | I11: Decided (accepted Oct 28; was proposed) | K11: 5
A12: R009 | B12: Not started | C12: Gate (show only if) | D12: Car gate | E12: Has a car = No | F12: Car insurance, gas, maintenance, registration, tolls, parking, car wash and the car asset don't appear | G12: They appear; transit and Uber appear either way | I12: Decided (your Fields comment) | K12: 5
A13: R010 | B13: Not started | C13: Gate (show only if) | D13: Kids gate | E13: Dependents = 0 | F13: All Kids lines and the kid tax credits don't appear | G13: They appear | I13: Decided (your Fields comment) | K13: 5
A14: R011 | B14: Not started | C14: Gate (show only if) | D14: Pets gate | E14: Pets = 0 | F14: All Pet lines don't appear | G14: They appear | I14: Decided (your Fields comment) | K14: 5
A15: R012 | B15: Not started | C15: Gate (show only if) | D15: Health coverage | E15: Coverage is not confirmed as HSA-eligible | F15: HSA rows (contribution, invested vs cash, HSA account type) don't appear | G15: They appear | I15: Decided (your Mockup comment) | K15: 5
A16: R013 | B16: Not started | C16: Gate (show only if) | D16: Health coverage | E16: Coverage doesn't include an FSA | F16: FSA rows don't appear | G16: They appear | I16: Decided (your Mockup comment) | K16: 5
A17: R014 | B17: Not started | C17: Gate (show only if) | D17: Income | E17: Employer doesn't offer ESPP or RSUs | F17: Equity pay fields don't appear | G17: Appear when ticked in the paycheck row's Secondary: 'Equity pay offered? ☐ ESPP ☐ RSU ☐ Options' (also listed in the gates hub) | I17: Decided (your comment: where would this gate be) | K17: 5
A18: R015 | B18: Not started | C18: Gate (show only if) | D18: Gates hub | E18: Always | F18: Profile has a 'What applies to me' panel listing every gate (car, kids, pets, housing, work, health, equity pay, couple, account types) with its answer. Changing one adds or removes those sections and jumps you there | G18: Each hidden area also shows a slim '+ Add [area]' link in its sub-tab, linked back to the hub | I18: Decided (your comment on R001) | K18: 5
A19: R016 | B19: Not started | C19: Gate (show only if) | D19: Student loan | E19: Private | F19: Repayment plan and PSLF fields don't appear | G19: Federal: they appear | I19: Decided (accepted Oct 28; was proposed) | K19: 5
A20: R017 | B20: Not started | C20: Gate (show only if) | D20: Investment account | E20: Account type picked | F20: Only the fields unique to that type appear (cost basis for brokerage, Roth basis for Roth, invested vs cash for HSA) | I20: Decided (Oct 27: each type carries its own fields) | K20: 5
A21: R018 | B21: Not started | C21: Gate (show only if) | D21: Investment account | E21: Pretax | Roth | Both = Both | F21: Two balance boxes (pretax and Roth) | G21: One balance box | I21: Decided (accepted Oct 28; was proposed) | K21: 5
A22: R019 | B22: Not started | C22: Gate (show only if) | D22: Debt picker | E22: Always | F22: Top 4 shown: credit card, student loan, car loan, personal loan; Other opens the rest with search | I22: Decided (your Mockup comment) | K22: 5
A23: R020 | B23: Not started | C23: Gate (show only if) | D23: Credit card | E23: Payment = Custom | F23: Custom $ box appears | G23: Hidden | I23: Decided (your Mockup comment) | K23: 5
A24: R021 | B24: Not started | C24: Gate (show only if) | D24: Taxes | E24: Income type includes 1099 or self-employed | F24: Quarterly estimates and self-employment tax appear | G24: Hidden | I24: Decided (accepted Oct 28; was proposed) | K24: 5
A25: R022 | B25: Not started | C25: Gate (show only if) | D25: Goals | E25: Milestone = Barista FI | F25: Part-time income field appears | G25: Hidden | I25: Decided (Oct 7 FI definitions) | K25: 5
A26: R023 | B26: Not started | C26: Gate (show only if) | D26: Any sub-tab | E26: Layer = Secondary or Tertiary | F26: Fields stay behind the caret, collapsed by default | G26: Primary always visible | I26: Decided (Oct 28: detail behind carets) | K26: 5
A27: R024 | B27: Not started | C27: Default | D27: Every new row | E27: Row created | F27: All boxes start blank, never 0% or $0; computed results show '–' until inputs exist | H27: ProjectionLab shows '0 years to pay off' on a blank row | I27: Decided (screen review) | K27: 2
A28: R025 | B28: Not started | C28: Default | D28: Goals | E28: No return entered | F28: Return 7%, inflation 2%, withdrawal 4% | I28: Decided (Oct 28: your usual numbers) | K28: 2
A29: R026 | B29: Not started | C29: Default | D29: Goals | E29: Presets | F29: Return (already after inflation): 6% (conservative), 7% (default), 8% (optimistic), 12% (hopeful, no inflation taken out). Inflation: 2% (default), 3%. Withdrawal: 3%, 4% (default), 4.7%, 5.2% | I29: Decided (Oct 28) | K29: 2
A30: R027 | B30: Not started | C30: Default | D30: Coast FI retirement age | E30: Always | F30: Uses the FI target age if set; otherwise 60, editable in Plan > Goals as 'Retire by' | I30: Decided (Oct 28, from Claude Code's question) | K30: 2
A31: R028 | B31: Not started | C31: Default | D31: FI date investing | E31: Always | F31: Monthly surplus counts as invested until an investing split is entered | I31: Decided (Oct 28, from Claude Code's question) | K31: 2
A32: R029 | B32: Not started | C32: Default | D32: Plan | E32: Always | F32: A 'These are big deals' card shows the FI date under each preset side by side, so the client sees how much one assumption moves it | I32: Decided (Oct 28) | K32: 2
A33: R030 | B33: Not started | C33: Default | D33: Goals | E33: No pace picked | F33: Likely (the default presets); Optimistic and Pessimistic use the 8% and 6% presets | I33: Decided (Oct 28, replaces Optimistic default) | K33: 2
A34: R031 | B34: Not started | C34: Default | D34: Goals | E34: No life expectancy | F34: 90 | H34: ProjectionLab uses 85 | I34: Decided (accepted Oct 28; was proposed) | K34: 2
A35: R032 | B35: Not started | C35: Default | D35: Goals | E35: No retirement spending | F35: Equals current spending | I35: Decided (accepted Oct 28; was proposed) | K35: 2
A36: R033 | B36: Not started | C36: Default | D36: Goals | E36: Social Security not set | F36: Full scheduled benefit (likely case), never zero by default | I36: Decided (Oct 2) | K36: 2
A37: R034 | B37: Not started | C37: Default | D37: Engine | E37: Always | F37: Real (today's) dollars; nominal is a toggle | I37: Decided (Oct 2) | K37: 2
A38: R035 | B38: Not started | C38: Default | D38: Split by | E38: Roommates entered | F38: Every shared Needs line defaults to split by roommates + 1 | G38: Client can override per line or just type 'my share' | I38: Decided (your Fields comment) | K38: 2
A39: R036 | B39: Not started | C39: Default | D39: Housing = Family | E39: Housing line | F39: Defaults to 'Covered by someone' with Covered by = Parents | I39: Decided (accepted Oct 28; was proposed) | K39: 2
A40: R037 | B40: Not started | C40: Default | D40: APR = Not sure | E40: Debt row | F40: Fills the typical rate for that debt type from Reference data (Federal Reserve G.19), labeled Guess | H40: Credit card 22.15%, personal loan 11.86%, car 7.14% | I40: Decided (Oct 28; Guess wins over Roughly here) | K40: 2
A41: R038 | B41: Not started | C41: Default | D41: Min payment | E41: Credit card balance and APR exist | F41: Minimum is computed and shown in Primary; client can overwrite with the statement number | I41: Decided (your Mockup comment) | K41: 2
A42: R039 | B42: Not started | C42: Default | D42: Credit card payment | E42: No choice made | F42: Minimum | I42: Decided (accepted Oct 28; was proposed) | K42: 2
A43: R040 | B43: Not started | C43: Default | D43: Tax set-aside | E43: Self-employed, no % entered | F43: 25% | I43: Decided (accepted Oct 28; was proposed) | K43: 2
A44: R041 | B44: Not started | C44: Default | D44: Session length | E44: Not set | F44: 60 minutes | I44: Decided (accepted Oct 28; was proposed) | K44: 2
A45: R042 | B45: Not started | C45: Default | D45: Low balance line | E45: Not set | F45: $500 | I45: Decided (accepted Oct 28; was proposed) | K45: 2
A46: R043 | B46: Not started | C46: Default | D46: Filing status | E46: Solo, not set | F46: Single (marked Coach infers) | G46: Couple: Married filing jointly (marked Coach infers) | I46: Decided (accepted Oct 28; was proposed) | K46: 2
A47: R044 | B47: Not started | C47: Default | D47: Period selector | E47: Spending opened | F47: Monthly | I47: Decided (Oct 22: monthly default) | K47: 2
A48: R045 | B48: Not started | C48: Entry | D48: Any amount with a 'per' picker | E48: Amount entered per paycheck, week, month or year | F48: Stored as monthly; shown back in the unit it was entered | I48: Decided (Sept 23: any way a number can be given) | K48: 3-6
A49: R046 | B49: Not started | C49: Entry | D49: Income | E49: Only take-home entered | F49: Gross is solved and marked Computed | G49: Only gross entered: take-home solved. Both: both kept, difference flagged if they don't reconcile | I49: Decided (Oct 2) | K49: 3-6
A50: R047 | B50: Not started | C50: Entry | D50: Pickers | E50: Typing | F50: Matches start after 1 letter; Enter picks the top match; free text allowed as 'Other' | I50: Decided (Oct 27: type a little and pick) | K50: 3-6
A51: R048 | B51: Not started | C51: Entry | D51: Every section | E51: Client has something not on the list | F51: 'Other' row with name, amount, type is always available | I51: Decided (session gaps) | K51: 3-6
A52: R049 | B52: Not started | C52: Entry | D52: Car loan / mortgage | E52: Entered on either the asset or the debt | F52: Same record shows in both places; editing one edits the other | I52: Decided (screen review) | K52: 3-6
A53: R050 | B53: Not started | C53: Entry | D53: Calendar | E53: Credit card or loan has a due day | F53: Payment appears on the calendar automatically, repeating monthly | I53: Decided (screen review) | K53: 3-6
A54: R051 | B54: Not started | C54: Entry | D54: Irregular costs | E54: Yearly cost and month entered | F54: Lands on the calendar in that month and creates a monthly set-aside | I54: Decided (accepted Oct 28; was proposed) | K54: 3-6
A55: R052 | B55: Not started | C55: Entry | D55: Budget actuals | E55: Calendar entries marked Got it / Paid | F55: Feed the budget line's Actual | I55: Decided (Oct 16 ice cream sandwich) | K55: 3-6
A56: R053 | B56: Not started | C56: Entry | D56: Parking lot | E56: Note converted to a field | F56: Note is struck through and links to that field | I56: Decided (accepted Oct 28; was proposed) | K56: 3-6
A57: R054 | B57: Not started | C57: Status and confidence | D57: Every input | E57: Value typed | F57: Status = Know it unless changed | I57: Decided (accepted Oct 28; was proposed) | K57: 1-3
A58: R055 | B58: Not started | C58: Status and confidence | D58: Every input | E58: Status picked | F58: One of: Know it, Roughly, Not sure, Will email, Not now, Not for me, Computed | I58: Decided (Oct 27, list pending your final OK) | K58: 1-3
A59: R056 | B59: Not started | C59: Status and confidence | D59: Status = Roughly | E59: Any field | F59: Counts as done, shows ≈, gets a next check date | I59: Decided (Oct 27) | K59: 1-3
A60: R057 | B60: Not started | C60: Status and confidence | D60: Status = Not sure | E60: Any field | F60: App fills a typical value labeled Guess. Different from Roughly: Roughly is the client's own ballpark, Guess is the app's number. Counts toward core but flagged | I60: Decided (accepted Oct 28; was proposed) | K60: 1-3
A61: R058 | B61: Not started | C61: Status and confidence | D61: Status = Will email | E61: Any field | F61: Added to homework list with the field name; counts as not done | I61: Decided (homework) | K61: 1-3
... A69: R066 | B69: Not started | C69: Completion | D69: Counting | E69: Field is gated out | F69: Not counted at all | I69: Decided | K69: 5
A70: R067 | B70: Not started | C70: Completion | D70: Counting | E70: Know it, Roughly, Not for me, Computed | F70: Done | G70: Not sure counts for core only; Will email and Not now are not done | I70: Decided (accepted Oct 28; was proposed) | K70: 5
A71: R068 | B71: Not started | C71: Completion | D71: Fast Track | E71: All Fast Track fields done | F71: Every lens turns on (net worth, savings rate, DRAFTT, FI date) | I71: Decided (your comment: enough to turn on every lens) | K71: 5
A72: R069 | B72: Not started | C72: Completion | D72: Fast Track accuracy | E72: Fast Track result vs full-detail result | F72: Target: within $100/month of the full answer. Track the gap after each full session | I72: Decided (your comment) | K72: 5
A73: R070 | B73: Not started | C73: Completion | D73: Metrics | E73: Inputs missing | F73: Metric card shows 'Locked: needs 2 numbers' and jumps to them | I73: Decided (metrics unlocked) | K73: 5
A74: R071 | B74: Not started | C74: Order and priority | D74: Next 3 numbers | E74: Always | F74: Rank empty, Not sure and Not now fields by how much they move FI date and core metrics; ignore gated-out fields | I74: Decided (Oct 7 dependency ranking) | K74: 7
A75: R072 | B75: Not started | C75: Order and priority | D75: Next 3 numbers | E75: Two fields tie | F75: Primary before Secondary, then the order the field appears on screen | I75: Decided (accepted Oct 28; was proposed) | K75: 7
A76: R073 | B76: Not started | C76: Order and priority | D76: Materiality | E76: A field's effect is under $100/year | F76: Never in Next 3; goes to the Small wins tab | I76: Decided (Oct 2) | K76: 7
A77: R074 | B77: Not started | C77: Order and priority | D77: Debt payoff order | E77: Avalanche | F77: Highest APR first | G77: Snowball: smallest balance first. Stress: highest stress first, ties by APR | I77: Decided (Oct 2) | K77: 7
A78: R075 | B78: Not started | C78: Order and priority | D78: Promo rates | E78: 0% promo ends within 60 days | F78: Card jumps to the top of payoff order and shows a warning | I78: Decided (accepted Oct 28; was proposed) | K78: 7
A79: R076 | B79: Not started | C79: Order and priority | D79: Guide me | E79: Turned on | F79: Follows the session 1 curriculum order; skips gated-out and done fields | I79: Decided (Oct 7) | K79: 7
A80: R077 | B80: Not started | C80: Visibility | D80: Client view | E80: On | F80: Hides private notes, stress ratings, coach-only fields, the gear, other clients' names; text 15% bigger | I80: Decided (session gaps) | K80: 4
A81: R078 | B81: Not started | C81: Visibility | D81: Coach tools | E81: Always | F81: Behind the gear, never on a main tab | I81: Decided (Oct 27) | K81: 4
A82: R079 | B82: Not started | C82: Visibility | D82: Private notes | E82: Always | F82: Never shown in client view, the one-pager, exports to the client or the pre-call form | I82: Decided (session gaps) | K82: 4
A83: R080 | B83: Not started | C83: Visibility | D83: Colors | E83: Any difference or warning | F83: Never red; use neutral and calm tones | I83: Decided (nine tiles never red) | K83: 4
A84: R081 | B84: Not started | C84: Visibility | D84: Pre-call form | E84: Start of the client program | F84: You fill Level 1 yourself in session 1; the client-facing link is built later with the same questions | I84: Decided (your comment: I'll be filling it out to start) | K84: 4
A85: R082 | B85: Not started | C85: Data safety | D85: Delete row | E85: Clicked | F85: Row removed, 'Undo' toast for 10 seconds | I85: Decided (screen review) | K85: 1
A86: R083 | B86: Not started | C86: Data safety | D86: Reset row | E86: Clicked | F86: All fields blank, status cleared, row kept; Undo toast | I86: Decided | K86: 1
A87: R084 | B87: Not started | C87: Data safety | D87: Reset section | E87: Clicked | F87: Confirm dialog naming the section; Undo toast | I87: Decided | K87: 1
A88: R085 | B88: Not started | C88: Data safety | D88: Reset client | E88: Clicked | F88: Must type the client's name; snapshot taken first | I88: Decided | K88: 1
A89: R086 | B89: Not started | C89: Data safety | D89: Autosave | E89: Any change | F89: Saved within 1 second; 'Unsaved' shown if it fails; warning before closing the tab | I89: Decided (session gaps) | K89: 1
... A96: R093 | B96: Not started | C96: Calendar | D96: Partial | E96: Some of the money came or was paid | F96: Enter the amount so far; the rest stays Planned on the same entry. Update it later instead of starting over | I96: Decided (your comment on R048) | K96: 6
A97: R094 | B97: Not started | C97: Calendar | D97: Didn't happen | E97: Clicked | F97: Entry kept, greyed, counted as $0 actual so the miss shows in month-end close | G97: Moved: pick a new date, original date keeps a faint marker | I97: Decided (accepted Oct 28; was proposed) | K97: 6
A98: R095 | B98: Not started | C98: Calendar | D98: Wins | E98: A payoff date, milestone or FI step is reached in the projection | F98: Win chip appears on that date automatically | I98: Decided (your comment) | K98: 6
A99: R096 | B99: Not started | C99: Calendar | D99: Low balance | E99: End-of-day balance below the line | F99: Day shows ⚠ and Home shows the first such day | I99: Decided (accepted Oct 28; was proposed) | K99: 6
A100: R097 | B100: Not started | C100: Calendar | D100: Repeats | E100: Twice a month | F100: 1st and 15th unless days are set | I100: Decided (accepted Oct 28; was proposed) | K100: 6
A101: R098 | B101: Not started | C101: Calendar | D101: Paychecks | E101: Every-2-weeks pay lands 3 times in a month | F101: Month marked 'bonus paycheck month' | I101: Decided (Oct 22) | K101: 6
A102: R099 | B102: Not started | C102: Paid with (bill to card) | D102: Needs lines, calendar entries, irregular costs | E102: Always | F102: Every bill can carry 'Paid with ▾': checking, savings, or any credit card on file. Tertiary by default | I102: Decided (your message: link a bill to a credit card, tertiary) | K102: 6
A103: R100 | B103: Not started | C103: Paid with (bill to card) | D103: Where it lives | E103: Always | F103: Paid with sits at the top of the row's More ▸ area, so it's 3 clicks from any bill | I103: Decided (Oct 28) | K103: 6
A104: R101 | B104: Not started | C104: Paid with (bill to card) | D104: Paid with = a credit card | E104: Bill linked | F104: The charge adds to that card's expected balance on its date; the calendar shows it on the card, not on checking; the card's payment day pulls the total | I104: Decided (accepted Oct 28; was proposed) | K104: 6
A105: R102 | B105: Not started | C105: Paid with (bill to card) | D105: Promote to Secondary | E105: Client says most spending goes on cards (Profile toggle) | F105: 'Paid with' moves up to Secondary on every line | G105: Stays Tertiary | I105: Decided (accepted Oct 28; was proposed) | K105: 6
A106: R103 | B106: Not started | C106: Paid with (bill to card) | D106: Card row | E106: Bills are linked to the card | F106: Card's Secondary shows 'Bills on this card: 6, $412/mo' with a list | I106: Decided (accepted Oct 28; was proposed) | K106: 6
A107: R104 | B107: Not started | C107: Paid with (bill to card) | D107: Card paid in full monthly | E107: Pay = In full | F107: Linked bills count as spending, not debt; no interest | G107: Carrying a balance: linked bills add to the payoff projection | I107: Decided (accepted Oct 28; was proposed) | K107: 6
A108: R105 | B108: Not started | C108: Staples (same everywhere) | D108: Every section | E108: Always | F108: One '+ Add [thing]' button in the same spot (bottom left of the section), same look | I108: Decided (your message: uniform staples) | K108: 3
A109: R106 | B109: Not started | C109: Staples (same everywhere) | D109: Every add picker | E109: Clicked | F109: Top 4 types as big buttons, Other opens the rest with search, 'Name your own' at the end | I109: Decided (your Mockup comment, made universal) | K109: 3
A110: R107 | B110: Not started | C110: Staples (same everywhere) | D110: Every row | E110: Always | F110: Same anatomy left to right: type/name, amount, per, owner (couples), status, ⧉ ↺ 🗑, ▸ More | I110: Decided | K110: 3
A111: R108 | B111: Not started | C111: Staples (same everywhere) | D111: Quick add | E111: Top bar | F111: '+ Add anything' box: type 'Netflix 15.99 monthly' or 'Chase card 3200 at 24%' and it picks the type and section; you confirm | I111: Decided (accepted Oct 28; was proposed) | K111: 3
A112: R109 | B112: Not started | C112: Staples (same everywhere) | D112: Add from anywhere | E112: Adding from Home, calendar or a chart | F112: Opens the same add picker and drops the row in its home section; no screen switch | I112: Decided (accepted Oct 28; was proposed) | K112: 3
A113: R110 | B113: Not started | C113: Staples (same everywhere) | D113: Every section footer | E113: Always | F113: Total, count, completion bar in the same spot | I113: Decided (accepted Oct 28; was proposed) | K113: 3
...

Sheet Rules summary
A1: Rule type | B1: Rules | C1: Proposed (need your OK)
A2: Gate (show only if) | B2: =COUNTIF(Rules!C:C,A2) | C2: =COUNTIFS(Rules!C:C,A2,Rules!I:I,"Proposed*")
A3: Default | B3: =COUNTIF(Rules!C:C,A3) | C3: =COUNTIFS(Rules!C:C,A3,Rules!I:I,"Proposed*")
A4: Entry | B4: =COUNTIF(Rules!C:C,A4) | C4: =COUNTIFS(Rules!C:C,A4,Rules!I:I,"Proposed*")
A5: Status and confidence | B5: =COUNTIF(Rules!C:C,A5) | C5: =COUNTIFS(Rules!C:C,A5,Rules!I:I,"Proposed*")
A6: Completion | B6: =COUNTIF(Rules!C:C,A6) | C6: =COUNTIFS(Rules!C:C,A6,Rules!I:I,"Proposed*")
A7: Order and priority | B7: =COUNTIF(Rules!C:C,A7) | C7: =COUNTIFS(Rules!C:C,A7,Rules!I:I,"Proposed*")
A8: Visibility | B8: =COUNTIF(Rules!C:C,A8) | C8: =COUNTIFS(Rules!C:C,A8,Rules!I:I,"Proposed*")
A9: Data safety | B9: =COUNTIF(Rules!C:C,A9) | C9: =COUNTIFS(Rules!C:C,A9,Rules!I:I,"Proposed*")
A10: Calendar | B10: =COUNTIF(Rules!C:C,A10) | C10: =COUNTIFS(Rules!C:C,A10,Rules!I:I,"Proposed*")
A11: Paid with (bill to card) | B11: =COUNTIF(Rules!C:C,A11) | C11: =COUNTIFS(Rules!C:C,A11,Rules!I:I,"Proposed*")
A12: Staples (same everywhere) | B12: =COUNTIF(Rules!C:C,A12) | C12: =COUNTIFS(Rules!C:C,A12,Rules!I:I,"Proposed*")
A13: Bulk select | B13: =COUNTIF(Rules!C:C,A13) | C13: =COUNTIFS(Rules!C:C,A13,Rules!I:I,"Proposed*")
... A20: Copy and look | B20: =COUNTIF(Rules!C:C,A20) | C20: =COUNTIFS(Rules!C:C,A20,Rules!I:I,"Proposed*")
A21: Total | B21: =SUM(B2:B20) | C21: =SUM(C2:C20)

Sheet Math
A1: Math: every computed number
A2: ID | B2: Name | C2: Formula | D2: Inputs | E2: When something's missing | F2: Notes / example
A3: CONVENTIONS
A4: M00 | B4: Units | C4: All money stored monthly in today's dollars; rates stored as annual decimals (7% = 0.07) | F4: Engine works in real dollars; nominal is a display toggle
A5: M01 | B5: Monthly from any period | C5: weekly × 52/12; every 2 weeks × 26/12; twice a month × 2; yearly / 12; per paycheck uses pay frequency | D5: amount, period | E5: Missing period → treat as monthly and mark Roughly
A6: M02 | B6: Real return | C6: Return presets are already after inflation: 6%, 7%, 8% are real returns. 12% is the hopeful optimistic case with no inflation taken out | D6: return preset | F6: Inflation (2% or 3%) is used only for the nominal display toggle, Social Security and debt in today's dollars
A7: INCOME AND TAXES
A8: M10 | B8: Federal income tax | C8: Taxable = annual gross − pretax deductions − standard deduction (floor 0); apply brackets from Reference data | D8: gross, pretax deductions, filing status, year | E8: No filing status → Single (solo) or Married jointly (couple) | F8: v1 is federal plus FICA only
A9: M11 | B9: FICA | C9: 6.2% Social Security up to the wage base + 1.45% Medicare (+0.9% over $200k single) | D9: gross, year | F9: Self-employed: 15.3% on 92.35% of net earnings, half deductible
A10: M12 | B10: Take-home from gross | C10: gross − federal tax − FICA − pretax deductions (− state when added later) | D10: M10, M11
A11: M13 | B11: Gross from take-home | C11: Solve M12 backwards by bisection to the nearest $1 | D11: take-home, deductions | F11: Marked Computed
A12: M14 | B12: Effective and marginal tax rate | C12: Effective = (federal + FICA) / gross. Marginal = bracket of the last dollar + FICA rate | D12: M10, M11
A13: M15 | B13: Employer match ($/yr) | C13: min(contribution %, match cap %) × match % × gross | D13: 401(k) %, match formula, gross | F13: Unvested part shown separately
A14: M16 | B14: Variable income safe budget | C14: lowest month × (1 − tax set-aside %) | D14: lowest month, set-aside | E14: Missing lowest month → typical month × 0.75, marked Guess
A15: M17 | B15: Real hourly wage | C15: (take-home − work costs) / (paid hours + commute + prep hours), monthly | D15: income, work costs, hours | E15: Missing hours → show 'needs hours' instead of a number
A16: SPENDING
A17: M20 | B17: Line monthly amount | C17: M01 applied to each line; accrual view spreads prepaid and yearly costs across months covered | D17: line amount, period, covers
A18: M21 | B18: My share | C18: If 'my share' typed → use it. Else amount × (1 − covered %) / split by | D18: amount, who pays, covered, split | E18: Split by defaults to roommates + 1
A19: M22 | B19: Support received | C19: Σ (amount − my share) where covered by someone else | D19: M21 across lines | F19: Shown on Report; 'what if it stops' = this added to spending
A20: M23 | B20: Fixed floor | C20: Σ my share of lines with Amount = Fixed | D20: M21 | F20: Feeds runway and Lean FI
A21: M24 | B21: Irregular set-aside | C21: yearly cost / 12 | D21: yearly cost
A22: M25 | B22: Estimate vs actual | C22: difference = actual − estimate; % = difference / estimate | D22: estimate, actual | E22: Estimate 0 → show $ only
A23: M26 | B23: Gut accuracy | C23: Average of |actual − Gut or Rough| / actual across months, per line and overall | D23: history | E23: Fewer than 1 closed month → hidden
A24: M27 | B24: Monthly surplus | C24: take-home − total my-share spending − debt payments not already in spending | D24: M12, M21, debts
A25: M28 | B25: Savings rate (headline) | C25: (surplus + after-tax savings in the budget) / take-home | D25: M27 | F25: Gross version in Show the math: (all saving incl. pretax and match) / gross
A26: M29 | B26: DRAFTT shares | C26: Each letter's total / take-home; Taxes and Therapy optional | D26: lines tagged by letter | F26: Proportions only, no verdict colors
A27: M2A | B27: Housing % | C27: housing my-share / take-home | D27: rent or mortgage, utilities | F27: Reference line at 35%
A28: M2B | B28: Accrual spread and prepaid balance | C28: monthly = amount / months covered; prepaid left = amount − monthly × months elapsed | D28: amount, date paid, months covered
A29: DEBT
A30: M30 | B30: Credit card minimum payment | C30: max($25, 1% of balance + one month's interest), capped at the balance | D30: balance, APR | E30: Statement number overrides | F30: Common issuer formula; confirm
A31: M31 | B31: Payoff months | C31: n = −ln(1 − r·B/P) / ln(1 + r), r = APR/12; round up. 0% → B/P | D31: balance, APR, payment | E31: P ≤ r·B → 'This payment never pays it off' and the payment needed | F31: Sheets: =ROUNDUP(NPER(APR/12, −P, B), 0)
A32: M32 | B32: Total interest | C32: n (unrounded) × P − B | D32: M31 | F32: This formula is the source of truth for one debt. The month-by-month simulation (M34) is only for payoff order with extra payments; it may differ by a few dollars from rounding
A33: M33 | B33: Payday or fee APR | C33: fee / amount borrowed × periods per year | D33: fee, amount, period
A34: M34 | B34: Payoff order with extra payment | C34: Simulate monthly: pay minimums, put extra on the first debt in order; when one clears, roll its payment forward | D34: debts, extra, order | F34: Order: avalanche (APR), snowball (balance), stress (rating, ties by APR)
A35: M35 | B35: Utilization | C35: Σ card balances / Σ limits | D35: cards | E35: No limits → hidden
A36: M36 | B36: Debt-to-income | C36: monthly debt payments / gross monthly income | D36: debts, gross
A37: M37 | B37: Promo solver | C37: Payment needed to clear a 0% balance by the promo end = balance / months left | D37: balance, promo end
A38: ASSETS AND NET WORTH
A39: M40 | B39: Total net worth | C39: Σ assets (vested only) − Σ debts | D39: all accounts
A40: M41 | B40: Liquid net worth | C40: cash + taxable brokerage + Roth contribution basis − consumer debt | D40: accounts, debts | F40: Excludes home, car, retirement growth
A41: M42 | B41: Runway months | C41: liquid cash / monthly spending (also shown vs fixed floor) | D41: cash, M27
A42: M43 | B42: Rule of 5 | C42: target months = age / 5; target $ = target months × monthly spending; keep-pace add = monthly spending / 60; gap = target − emergency cash | D42: age, spending, cash | F42: Confirmed Oct 28
A43: M44 | B43: Contribution limit used | C43: year-to-date contributions / limit for that account type and age | D43: contributions, Reference data
A44: GOALS AND PROJECTION
A45: M50 | B45: FI number | C45: annual retirement spending / withdrawal rate | D45: spending, WR | F45: 4% → 25×
A46: M51 | B46: Lean FI number | C46: annual FAT spending / withdrawal rate | D46: Food, Accommodation, Transportation lines
A47: M52 | B47: Barista FI number | C47: (annual spending − annual part-time income) / withdrawal rate | D47: part-time income
A48: M53 | B48: FI date | C48: Monthly: invested × (1 + real return)^(1/12) + monthly investing; first month invested ≥ FI number | D48: invested, monthly investing, M02, M50 | E48: Never reached in 70 years → 'not on this path' plus solver | F48: Monthly investing = surplus to investing + pretax contributions + match
A49: M54 | B49: Coast FI | C49: Coast number at age a = FI number / (1 + real return)^(retire age − a); reached when invested ≥ it. Retire age = FI target age, else 60 | D49: M50, M02, ages | F49: Computed properly, not a fixed multiple
A50: M55 | B50: % to each FI | C50: invested / each FI number | D50: M50-M54
A51: M56 | B51: These are big deals | C51: Run M53 once per preset (return, inflation, withdrawal) holding the rest at default; biggest mover = largest date change | D51: M53
A52: M57 | B52: Solvers | C52: Bisection on M53 for spending, income or monthly saving that hits FI by a target age | D52: M53
A53: M58 | B53: Money as time | C53: hours = amount / real hourly wage; FI days = amount / (annual spending / 365) | D53: M17, spending
A54: CALENDAR
A55: M60 | B55: Running balance | C55: start + Σ in − Σ out per day; Maybe entries excluded unless counted; variable-date items spread evenly | D55: entries
A56: M61 | B56: Bonus paycheck months | C56: Months with 3 paydays for every-2-weeks pay | D56: pay dates

Sheet Reference data
A1: Reference data: presets, limits, rates, lists
A2: Item | B2: Value | C2: Source | D2: Status
A3: PRESETS (your numbers)
A4: Return (after inflation) | B4: 6% conservative · 7% default · 8% optimistic · 12% hopeful (no inflation taken out) | C4: Your Oct 28 answers | D4: Confirmed by you
A5: Inflation | B5: 2% default · 3% | C5: Your Oct 28 defaults | D5: Confirmed by you
A6: Withdrawal rate | B6: 3% · 4% default · 4.7% · 5.2% | C6: Your Oct 28 defaults | D6: Confirmed by you
A7: 2026 LIMITS
A8: 401(k), 403(b), 457, TSP deferral | B8: $24,500; catch-up 50+ $8,000; ages 60-63 $11,250 | C8: IRS Notice 2025-67, via 401k Specialist | D8: Confirm
A9: IRA (Roth or Traditional) | B9: $7,500; catch-up 50+ $1,100 | C9: IRS Notice 2025-67 | D9: Confirm
A10: Total defined contribution (415c) | B10: $72,000 | C10: IRS Notice 2025-67 | D10: Confirm
A11: HSA | B11: $4,400 self-only · $8,750 family · catch-up 55+ $1,000 | C11: IRS, via HR Morning | D11: Confirm
A12: 2026 TAXES
A13: Standard deduction | B13: Single $16,100 · Married jointly $32,200 | C13: IRS 2026 inflation adjustments, via Journal of Accountancy | D13: Confirm
A14: Brackets, single (income over) | B14: 10% $0 · 12% $12,400 · 22% $50,400 · 24% $105,700 · 32% $201,775 · 35% $256,225 · 37% $640,600 | C14: Same | D14: Confirm
A15: Brackets, married jointly (income over) | B15: 10% $0 · 12% $24,800 · 22% $100,800 · 24% $211,400 · 32% $403,550 · 35% $512,450 · 37% $768,700 | C15: Same | D15: Confirm
A16: Social Security wage base | B16: $184,500 | C16: SSA 2026 announcement | D16: Confirm
A17: FICA rates | B17: 6.2% Social Security · 1.45% Medicare · +0.9% over $200k single / $250k joint | C17: Statutory | D17: Confirm
A18: TYPICAL RATES (used when the client says 'not sure', always labeled Guess)
A19: Credit card APR | B19: 22.15% (accounts paying interest); 20.94% all accounts | C19: Federal Reserve G.19, Q2 2026 (May 2026), released Aug 7 2026 | D19: Confirmed (Fed source)
A20: Personal loan APR | B20: 11.86% (24-month, commercial banks) | C20: Federal Reserve G.19, Q2 2026 | D20: Confirmed (Fed source)
A21: Car loan APR | B21: 7.14% (60-month new car); 6.97% (72-month) | C21: Federal Reserve G.19, Q2 2026 | D21: Confirmed (Fed source)
A22: Federal student loan rate | B22: Depends on year borrowed; ask | C22: Placeholder | D22: Confirm
A23: Tax set-aside (self-employed) | B23: 25% | C23: Rule of thumb | D23: Confirm
A24: Low balance line | B24: $500 | C24: Accepted rule | D24: Confirmed
A25: CATEGORY DEFAULTS
A26: Rent or mortgage | B26: Accommodation · Fixed amount · Fixed date
A27: Electric, gas, water | B27: Accommodation · Variable amount · Fixed date
A28: Internet, phone | B28: Accommodation / Other · Fixed amount · Fixed date
A29: Renters or home insurance | B29: Accommodation · Fixed amount · Fixed date
A30: Groceries, dining out, coffee | B30: Food · Variable amount · Variable date
A31: Car insurance | B31: Transportation · Fixed amount · Fixed date · car gate
A32: Gas or charging, tolls, parking | B32: Transportation · Variable amount · Variable date · car gate
A33: Car maintenance, registration | B33: Transportation · Variable / Fixed amount · Variable date · car gate
A34: Transit, Uber | B34: Transportation · Variable amount · Variable date
A35: Therapy | B35: Therapy · Fixed amount · Fixed date
A36: Subscriptions | B36: Other · Fixed amount · Fixed date
A37: Wants, travel, gifts | B37: Wants · Variable amount · Variable date
... A39: Pet lines | B39: Other · mostly Variable · pets gate
A40: LISTS
A41: Debt types (top 4 first) | B41: Credit card, Student loan, Car loan, Personal loan · Other: medical, family or friend, BNPL, payday or cash advance, tax, 401(k) loan, business, name your own
A42: Investment account types | B42: 401(k), 403(b), 457, TSP, Roth IRA, Traditional IRA, Rollover IRA, SEP, Solo 401(k), HSA, 529, Brokerage, Crypto, Other
A43: Cash account types | B43: Checking, Savings or HYSA, Money market, CD, Cash on hand
A44: Statuses | B44: Know it, Roughly, Not sure (Guess), Will email, Not now, Not for me, Computed
A45: Calendar entry statuses | B45: Planned, Partial, Got it / Paid, Didn't happen, Moved

Sheet Fields
A1: SLAM field map: every input, by layer
A2: ID | B2: Build status | C2: Stage | D2: Area | E2: Secondary area | F2: Field | G2: Layer | H2: What it shows | I2: Purpose (why it's asked, what it unlocks) | J2: Features | K2: Who supplies | L2: Homework? | M2: Confidence tags allowed | N2: Weight | O2: Stress rating | P2: Scope | Q2: Notes / references | R2: Your comments | S2: Lives on (screen) | T2: Data type | U2: Allowed values | V2: Build phase
A3: F001 | B3: Not started | C3: Pre-call | D3: Profile | E3: About you | F3: First name | G3: Primary | H3: Text box | I3: Non financial. Personalizes copy and breadcrumb | K3: Client | M3: Know it | N3: Low | P3: Now | S3: My Money › Profile | T3: text | V3: 5
A4: F002 | B4: Not started | C4: Pre-call | D4: Profile | E4: About you | F4: Last name | G4: Primary | H4: Text box | I4: Non financial | K4: Client | M4: Know it | N4: Low | P4: Now | S4: My Money › Profile | T4: text | V4: 5
A5: F003 | B5: Not started | C5: Pre-call | D5: Profile | E5: About you | F5: Birth month and year | G5: Primary | H5: Month picker (calendar style) | I5: Computes age. Drives Rule of 5, FI timeline, account age rules (55, 59.5, 65) | K5: Client | M5: Know it | N5: High | P5: Now | S5: My Money › Profile | T5: date | V5: 5
A6: F004 | B6: Not started | C6: Pre-call | D6: Profile | E6: About you | F6: State | G6: Primary | H6: Type-and-pick dropdown | I6: Tax and benefit rules. Most clients NY | K6: Client | M6: Know it | N6: High | P6: Now | Q6: ProjectionLab asks country, state, locality up front | S6: My Money › Profile | T6: choice | V6: 5
A7: F005 | B7: Not started | C7: Pre-call | D7: Profile | E7: Household | F7: Solo or couple | G7: Primary | H7: Two big buttons | I7: Gates every Owner field and the partner rows | J7: Owner dropdown appears on every row when couple | K7: Client | M7: Know it | N7: High | P7: Now | S7: My Money › Profile | T7: text | V7: 5
A8: F006 | B8: Not started | C8: Pre-call | D8: Profile | E8: Household | F8: Partner first name | G8: Primary | H8: Text box | I8: Shown only for couples | K8: Client | M8: Know it | N8: Low | P8: Now | S8: My Money › Profile | T8: text | V8: 5
A9: F007 | B9: Not started | C9: Pre-call | D9: Profile | E9: Household | F9: Partner birth month and year | G9: Primary | H9: Month picker | I9: Partner age for joint timeline | K9: Client | M9: Know it | N9: High | P9: Now | S9: My Money › Profile | T9: date | V9: 5
A10: F008 | B10: Not started | C10: Pre-call | D10: Profile | E10: Household | F10: Dependents (count and ages) | G10: Secondary | H10: Stepper plus age boxes | I10: Taxes, needs, kid scenario blocks | K10: Client | M10: All | N10: Medium | P10: Now | S10: My Money › Profile | T10: whole number | V10: 5
A11: F009 | B11: Not started | C11: Pre-call | D11: Profile | E11: Work | F11: Work situation | G11: Primary | H11: Pick one: employed W-2, self-employed, between jobs, student, retired, mixed | I11: Situation gate. Fields that don't apply are absent, not hidden (no employer match when between jobs) | K11: Client | M11: Know it | N11: High | P11: Now | S11: My Money › Profile | T11: choice | U11: employed W-2, self-employed, between jobs, student, retired, mixed | V11: 5
A12: F010 | B12: Not started | C12: Pre-call | D12: Profile | E12: Car and pets | F12: Has a car / has pets | G12: Primary | H12: Two yes-or-no buttons | I12: Car gate and pets gate for Needs lines | K12: Client | M12: Know it | N12: High | P12: Now | S12: My Money › Profile | T12: text | V12: 5
A13: F011 | B13: Not started | C13: Pre-call | D13: Profile | E13: Work | F13: Income stability | G13: Tertiary | H13: 3-step slider (steady, varies, unpredictable) | I13: Adjusts the Rule of 5 emergency target | K13: Client | M13: All | N13: Medium | P13: Now | S13: My Money › Profile | T13: text | V13: 5
A14: F012 | B14: Not started | C14: Pre-call | D14: Profile | E14: Home | F14: Housing status | G14: Primary | H14: Pick one: rent, own, live with family, other | I14: Gates Needs housing rows and the home asset | K14: Client | M14: Know it | N14: High | P14: Now | S14: My Money › Profile | T14: choice | U14: rent, own, live with family, other | V14: 5
A15: F013 | B15: Not started | C15: Pre-call | D15: Profile | E15: Home | F15: Roommates (count) | G15: Secondary | H15: Stepper | I15: Default split count for every shared Needs line. Enables worst case where everything falls on the client | K15: Client | M15: All | N15: Medium | P15: Now | S15: My Money › Profile | T15: whole number | V15: 5
A16: F014 | B16: Not started | C16: Pre-call | D16: Profile | E16: Health | F16: Health coverage type | G16: Secondary | H16: Pick one: employer, ACA, parent's plan, Medicaid, none, other | I16: Lives in profile (decided Oct 18). Feeds HSA eligibility and early retirement healthcare | K16: Client | M16: All | N16: Medium | P16: Now | S16: My Money › Profile | T16: choice | U16: employer, ACA, parent's plan, Medicaid, none, other | V16: 5
A17: F015 | B17: Not started | C17: Pre-call | D17: Profile | E17: Accounts gate | F17: Which do you have today | G17: Primary | H17: Multiselect cards: cash, investments, home or car, debt | I17: Only checked areas appear. Every area gets a built-in 'I don't have this' | J17: Multiselect | K17: Client | M17: Know it | N17: High | P17: Now | Q17: ProjectionLab setup step 2 | S17: My Money › Profile | T17: choice | U17: cash, investments, home or car, debt | V17: 5
A18: F016 | B18: Not started | C18: Pre-call | D18: Profile | E18: Accounts gate | F18: How many of each type | G18: Primary | H18: Stepper per type | I18: Creates the rows up front (Oct 28 decision). Add or duplicate later | J18: Add, duplicate | K18: Client | M18: All | N18: High | P18: Now | S18: My Money › Profile | T18: whole number | V18: 5
A19: F017 | B19: Not started | C19: Session 1 | D19: Profile | E19: Contact | F19: Client email and phone | G19: Secondary | H19: Text boxes | I19: Coach use only. Never on client screens | K19: Client | M19: Know it | N19: Low | P19: Now | S19: My Money › Profile | T19: text | V19: 5
A20: F018 | B20: Not started | C20: Later | D20: Profile | E20: Money personality | F20: Money Mirror or personality quiz result | G20: Tertiary | H20: Link to quiz | I20: Coaching lens, not math | K20: Client | M20: All | N20: Low | P20: Later | S20: My Money › Profile | T20: text | V20: 5
A21: F019 | B21: Not started | C21: Fast Track | D21: Income | E21: Main income | F21: Take-home pay | G21: Primary | H21: Amount plus 'per' picker (paycheck, month, year) | I21: Core of savings rate, DRAFTT shares, FI date | J21: Enter gross, take-home, or both; app solves for the other | K21: Client | M21: All | N21: High | P21: Now | Q21: ProjectionLab setup skips income, so no FI date at the end of setup | S21: My Money › Income | T21: money | V21: 5
A22: F020 | B22: Not started | C22: Fast Track | D22: Income | E22: Main income | F22: Pay frequency | G22: Primary | H22: Pick one: weekly, every 2 weeks, twice a month, monthly | I22: Per-paycheck budget view and 'bonus' 3-paycheck months | K22: Client | M22: All | N22: High | P22: Now | S22: My Money › Income | T22: choice | U22: weekly, every 2 weeks, twice a month, monthly | V22: 5
A23: F021 | B23: Not started | C23: Session 1 | D23: Income | E23: Main income | F23: Gross salary | G23: Secondary | H23: Amount plus 'per' picker | I23: Taxes, match, contribution limits | J23: Solved from take-home if blank (marked Computed) | K23: Client | M23: All | N23: High | P23: Now | S23: My Money › Income | T23: money | V23: 5
A24: F022 | B24: Not started | C24: Session 1 | D24: Income | E24: Main income | F24: Employer or source name | G24: Secondary | H24: Text box | I24: Labels the row | K24: Client | M24: Know it | N24: Low | P24: Now | S24: My Money › Income | T24: text | V24: 5
A25: F023 | B25: Not started | C25: Session 1 | D25: Income | E25: Main income | F25: Income type | G25: Secondary | H25: Pick one: W-2, 1099, business, side hustle, rental, benefits, other | I25: Tax treatment and stability | K25: Client | M25: All | N25: Medium | P25: Now | S25: My Money › Income | T25: choice | U25: W-2, 1099, business, side hustle, rental, benefits, other | V25: 5
A26: F024 | B26: Not started | C26: Session 1 | D26: Income | E26: Main income | F26: Bonus amount and month | G26: Secondary | H26: Amount plus month | I26: Windfall waterfall and cash flow calendar | K26: Client | L26: Often | M26: All | N26: Medium | P26: Now | S26: My Money › Income | T26: money | V26: 5
A27: F025 | B27: Not started | C27: Session 2+ | D27: Income | E27: Main income | F27: Expected raise % | G27: Tertiary | H27: Percent box | I27: Projection engine | K27: Coach guesstimate | M27: All | N27: Medium | P27: Now | S27: My Money › Income | T27: percent | V27: 5
A28: F026 | B28: Not started | C28: Session 1 | D28: Income | E28: Paycheck deductions | F28: 401(k) or 403(b) contribution % | G28: Secondary | H28: Percent box | I28: Savings rate (pretax counts), limit tracking | K28: Client | L28: Often | M28: All | N28: High | P28: Now | Q28: Paystub is the source | S28: My Money › Income | T28: percent | V28: 5
A29: F027 | B29: Not started | C29: Session 1 | D29: Income | E29: Paycheck deductions | F29: Health premium per paycheck | G29: Secondary | H29: Amount | I29: Take-home reconciliation | K29: Client | L29: Often | M29: All | N29: Medium | P29: Now | S29: My Money › Income | T29: money | V29: 5
A30: F028 | B30: Not started | C30: Session 2+ | D30: Income | E30: Paycheck deductions | F30: HSA or FSA per paycheck | G30: Tertiary | H30: Amount | I30: Savings rate and HSA limit | K30: Client | L30: Often | M30: All | N30: Medium | P30: Now | S30: My Money › Income | T30: money | V30: 5
A31: F029 | B31: Not started | C31: Session 2+ | D31: Income | E31: Paycheck deductions | F31: Other pretax deductions (commuter, life, disability) | G31: Tertiary | H31: Amount list | I31: Gross to net bridge | K31: Client | L31: Often | M31: All | N31: Low | P31: Now | S31: My Money › Income | T31: money | V31: 5
A32: F030 | B32: Not started | C32: Session 1 | D32: Income | E32: Employer match | F32: Match formula | G32: Secondary | H32: Two boxes: match % up to % of pay | I32: Free money check, waterfall step 1 | K32: Client | L32: Often | M32: All | N32: High | P32: Now | S32: My Money › Income | T32: text | V32: 5
A33: F031 | B33: Not started | C33: Session 2+ | D33: Income | E33: Employer match | F33: Vesting schedule | G33: Tertiary | H33: Pick: immediate, cliff, graded, plus years | I33: Unvested match shown separately but recognized (Oct 27) | K33: Client | L33: Often | M33: All | N33: Medium | P33: Now | S33: My Money › Income | T33: choice | U33: immediate, cliff, graded, plus years | V33: 5
A34: F032 | B34: Not started | C34: Session 1 | D34: Income | E34: Side income | F34: Side hustle income | G34: Secondary | H34: Amount with low, typical, high | I34: Variable income and Triple D | J34: Add, duplicate | K34: Client | M34: All | N34: Medium | P34: Now | S34: My Money › Income | T34: money | V34: 5
A35: F033 | B35: Not started | C35: Session 1 | D35: Income | E35: Partner income | F35: Partner take-home pay | G35: Primary | H35: Amount plus 'per' picker | I35: Couples only. Household savings rate | K35: Client | M35: All | N35: High | P35: Now | S35: My Money › Income | T35: money | V35: 5
A36: F034 | B36: Not started | C36: Session 2+ | D36: Income | E36: Benefits | F36: Unemployment or other benefits | G36: Tertiary | H36: Amount plus end date | I36: Between-jobs runway | K36: Client | M36: All | N36: Medium | P36: Now | S36: My Money › Income | T36: money | V36: 5
A37: F035 | B37: Not started | C37: Monthly | D37: Income | E37: Actuals | F37: Actual income from cash flow log | G37: Secondary | H37: Computed from log | I37: Estimated vs actual income | K37: Computed | M37: Computed | N37: High | P37: Now | Q37: Ice cream sandwich loop | S37: My Money › Income | T37: computed | V37: 5
A38: F036 | B38: Not started | C38: Session 1 | D38: Taxes | E38: Filing | F38: Filing status | G38: Secondary | H38: Pick one: single, married joint, married separate, head of household | I38: Federal brackets and standard deduction | K38: Client | M38: Know it | N38: High | P38: Now | S38: My Money › Taxes | T38: choice | U38: single, married joint, married separate, head of household | V38: 5
A39: F037 | B39: Not started | C39: Session 1 | D39: Taxes | E39: Filing | F39: Last year refund or amount owed | G39: Secondary | H39: Amount with refund or owed toggle | I39: Withholding check | K39: Client | L39: Often | M39: All | N39: Medium | P39: Now | S39: My Money › Taxes | T39: money | V39: 5
A40: F038 | B40: Not started | C40: Session 2+ | D40: Taxes | E40: Filing | F40: Quarterly estimates paid (1099) | G40: Tertiary | H40: Amount per quarter | I40: Self-employed only | K40: Client | L40: Often | M40: All | N40: Medium | P40: Now | S40: My Money › Taxes | T40: money | V40: 5
A41: F039 | B41: Not started | C41: Session 2+ | D41: Taxes | E41: Filing | F41: Itemizing or standard | G41: Tertiary | H41: Toggle | I41: Usually standard. Asked only if likely to itemize | K41: Coach infers | M41: All | N41: Low | P41: Now | S41: My Money › Taxes | T41: choice | V41: 5
A42: F040 | B42: Not started | C42: Computed | D42: Taxes | E42: Computed results | F42: Effective and marginal tax rate | G42: Secondary | H42: Computed tile | I42: Metric unlock. Federal plus FICA in v1 | K42: Computed | M42: Computed | N42: High | P42: Now | S42: My Money › Taxes | T42: computed | V42: 5
A43: F041 | B43: Not started | C43: Computed | D43: Taxes | E43: Computed results | F43: Self-employment tax | G43: Tertiary | H43: Computed tile | I43: 1099 income only | K43: Computed | M43: Computed | N43: Medium | P43: Now | S43: My Money › Taxes | T43: computed | V43: 5
A44: F042 | B44: Not started | C44: Parked | D44: Taxes | E44: Documents | F44: Paystub or 1040 reader | G44: Tertiary | H44: Upload | I44: Auto-fill deductions and filing info | K44: Client | M44: All | N44: Medium | P44: Parked | S44: My Money › Taxes | T44: text | V44: 5
A45: F043 | B45: Not started | C45: Fast Track | D45: Needs | E45: Total | F45: Gut monthly spending | G45: Primary | H45: One amount | I45: FI number (25x spending) on day one. Later compared to actual | K45: Client | M45: All | N45: High | P45: Now | Q45: Gut pass. Hold clients to their own words | S45: Spending › Budget | T45: money | V45: 6
A46: F044 | B46: Not started | C46: Session 1 | D46: Needs | E46: Accommodation | F46: Rent or mortgage payment | G46: Primary | H46: Amount plus frequency (weekly, monthly, yearly, one-off) | I46: DRAFTT and FAT shares, Lean FI (FAT costs), estimate vs actual | J46: Every line: covered/shared options, my share or split by count, should-get-this, N/A | K46: Client | M46: All | N46: High | P46: Now | Q46: Housing should be 35% of take-home (Oct 8) | S46: Spending › Budget | T46: money | V46: 6
A47: F045 | B47: Not started | C47: Session 1 | D47: Needs | E47: Accommodation | F47: Electric | G47: Secondary | H47: Amount plus frequency (weekly, monthly, yearly, one-off) | I47: DRAFTT and FAT shares, Lean FI (FAT costs), estimate vs actual | J47: Every line: covered/shared options, my share or split by count, should-get-this, N/A | K47: Client | M47: All | N47: Medium | P47: Now | Q47: Your comment: can be marked included in rent, or covered by someone (parents, other), tracking how much they cover | S47: Spending › Budget | T47: money | V47: 6
A48: F046 | B48: Not started | C48: Session 1 | D48: Needs | E48: Accommodation | F48: Gas and heat | G48: Secondary | H48: Amount plus frequency (weekly, monthly, yearly, one-off) | I48: DRAFTT and FAT shares, Lean FI (FAT costs), estimate vs actual | J48: Every line: covered/shared options, my share or split by count, should-get-this, N/A | K48: Client | M48: All | N48: Medium | P48: Now | S48: Spending › Budget | T48: money | V48: 6
A49: F047 | B49: Not started | C49: Session 1 | D49: Needs | E49: Accommodation | F49: Water and trash | G49: Secondary | H49: Amount plus frequency (weekly, monthly, yearly, one-off) | I49: DRAFTT and FAT shares, Lean FI (FAT costs), estimate vs actual | J49: Every line: covered/shared options, my share or split by count, should-get-this, N/A | K49: Client | M49: All | N49: Low | P49: Now | S49: Spending › Budget | T49: money | V49: 6
A50: F048 | B50: Not started | C50: Session 1 | D50: Needs | E50: Accommodation | F50: Internet | G50: Secondary | H50: Amount plus frequency (weekly, monthly, yearly, one-off) | I50: DRAFTT and FAT shares, Lean FI (FAT costs), estimate vs actual | J50: Every line: covered/shared options, my share or split by count, should-get-this, N/A | K50: Client | M50: All | N50: Low | P50: Now | Q50: Small wins candidate; Your comment: included in rent, or covered by someone, tracking how much | S50: Spending › Budget | T50: money | V50: 6
A51: F049 | B51: Not started | C51: Session 1 | D51: Needs | E51: Accommodation | F51: Renters or home insurance | G51: Secondary | H51: Amount plus frequency (weekly, monthly, yearly, one-off) | I51: DRAFTT and FAT shares, Lean FI (FAT costs), estimate vs actual | J51: Every line: covered/shared options, my share or split by count, should-get-this, N/A | K51: Client | M51: All | N51: Low | P51: Now | Q51: Should-get-this button when missing; Your comment: a 'we need to get this' button | S51: Spending › Budget | T51: money | V51: 6
A52: F050 | B52: Not started | C52: Session 1 | D52: Needs | E52: Food | F52: Groceries | G52: Primary | H52: Amount plus frequency (weekly, monthly, yearly, one-off) | I52: DRAFTT and FAT shares, Lean FI (FAT costs), estimate vs actual | J52: Every line: covered/shared options, my share or split by count, should-get-this, N/A | K52: Client | M52: All | N52: High | P52: Now | Q52: Weekly is a common way to answer | S52: Spending › Budget | T52: money | V52: 6
A53: F051 | B53: Not started | C53: Session 1 | D53: Needs | E53: Food | F53: Dining out and delivery | G53: Secondary | H53: Amount plus frequency (weekly, monthly, yearly, one-off) | I53: DRAFTT and FAT shares, Lean FI (FAT costs), estimate vs actual | J53: Every line: covered/shared options, my share or split by count, should-get-this, N/A | K53: Client | M53: All | N53: Medium | P53: Now | S53: Spending › Budget | T53: money | V53: 6
A54: F052 | B54: Not started | C54: Session 2+ | D54: Needs | E54: Food | F54: Coffee and snacks | G54: Tertiary | H54: Amount plus frequency (weekly, monthly, yearly, one-off) | I54: DRAFTT and FAT shares, Lean FI (FAT costs), estimate vs actual | J54: Every line: covered/shared options, my share or split by count, should-get-this, N/A | K54: Client | M54: All | N54: Low | P54: Now | S54: Spending › Budget | T54: money | V54: 6
A55: F053 | B55: Not started | C55: Session 1 | D55: Needs | E55: Transportation | F55: Car insurance | G55: Secondary | H55: Amount plus frequency (weekly, monthly, yearly, one-off) | I55: DRAFTT and FAT shares, Lean FI (FAT costs), estimate vs actual | J55: Every line: covered/shared options, my share or split by count, should-get-this, N/A | K55: Client | M55: All | N55: Medium | P55: Now | Q55: Only if Profile says they have a car (car gate); Your comment: separate by car gate | S55: Spending › Budget | T55: money | V55: 6
A56: F054 | B56: Not started | C56: Session 1 | D56: Needs | E56: Transportation | F56: Gas or charging | G56: Secondary | H56: Amount plus frequency (weekly, monthly, yearly, one-off) | I56: DRAFTT and FAT shares, Lean FI (FAT costs), estimate vs actual | J56: Every line: covered/shared options, my share or split by count, should-get-this, N/A | K56: Client | M56: All | N56: Medium | P56: Now | Q56: Only if Profile says they have a car (car gate) | S56: Spending › Budget | T56: money | V56: 6
A57: F055 | B57: Not started | C57: Session 1 | D57: Needs | E57: Transportation | F57: Car maintenance and repairs | G57: Secondary | H57: Amount plus frequency (weekly, monthly, yearly, one-off) | I57: DRAFTT and FAT shares, Lean FI (FAT costs), estimate vs actual | J57: Every line: covered/shared options, my share or split by count, should-get-this, N/A | K57: Client | M57: All | N57: Low | P57: Now | Q57: Only if Profile says they have a car (car gate). Yearly, shown monthly; Your comment: separate by car gate | S57: Spending › Budget | T57: money | V57: 6
A58: F056 | B58: Not started | C58: Session 2+ | D58: Needs | E58: Transportation | F58: Registration and inspection | G58: Tertiary | H58: Amount plus frequency (weekly, monthly, yearly, one-off) | I58: DRAFTT and FAT shares, Lean FI (FAT costs), estimate vs actual | J58: Every line: covered/shared options, my share or split by count, should-get-this, N/A | K58: Client | M58: All | N58: Low | P58: Now | Q58: Only if Profile says they have a car (car gate). Yearly | S58: Spending › Budget | T58: money | V58: 6
A59: F057 | B59: Not started | C59: Session 2+ | D59: Needs | E59: Transportation | F59: Tolls | G59: Tertiary | H59: Amount plus frequency (weekly, monthly, yearly, one-off) | I59: DRAFTT and FAT shares, Lean FI (FAT costs), estimate vs actual | J59: Every line: covered/shared options, my share or split by count, should-get-this, N/A | K59: Client | M59: All | N59: Low | P59: Now | Q59: Only if Profile says they have a car (car gate); Your comment: car-only items split out individually | S59: Spending › Budget | T59: money | V59: 6
A60: F058 | B60: Not started | C60: Session 2+ | D60: Needs | E60: Transportation | F60: Parking | G60: Tertiary | H60: Amount plus frequency (weekly, monthly, yearly, one-off) | I60: DRAFTT and FAT shares, Lean FI (FAT costs), estimate vs actual | J60: Every line: covered/shared options, my share or split by count, should-get-this, N/A | K60: Client | M60: All | N60: Low | P60: Now | Q60: Only if Profile says they have a car (car gate) | S60: Spending › Budget | T60: money | V60: 6
A61: F059 | B61: Not started | C61: Session 2+ | D61: Needs | E61: Transportation | F61: Car wash and supplies | G61: Tertiary | H61: Amount plus frequency (weekly, monthly, yearly, one-off) | I61: DRAFTT and FAT shares, Lean FI (FAT costs), estimate vs actual | J61: Every line: covered/shared options, my share or split by count, should-get-this, N/A | K61: Client | M61: All | N61: Low | P61: Now | Q61: Only if Profile says they have a car (car gate) | S61: Spending › Budget | T61: money | V61: 6
A62: F060 | B62: Not started | C62: Session 1 | D62: Needs | E62: Transportation | F62: Transit pass and fares | G62: Secondary | H62: Amount plus frequency (weekly, monthly, yearly, one-off) | I62: DRAFTT and FAT shares, Lean FI (FAT costs), estimate vs actual | J62: Every line: covered/shared options, my share or split by count, should-get-this, N/A | K62: Client | M62: All | N62: Medium | P62: Now | Q62: Everyone | S62: Spending › Budget | T62: money | V62: 6
A63: F061 | B63: Not started | C63: Session 1 | D63: Needs | E63: Transportation | F63: Uber, Lyft, taxis | G63: Secondary | H63: Amount plus frequency (weekly, monthly, yearly, one-off) | I63: DRAFTT and FAT shares, Lean FI (FAT costs), estimate vs actual | J63: Every line: covered/shared options, my share or split by count, should-get-this, N/A | K63: Client | M63: All | N63: Medium | P63: Now | Q63: Everyone | S63: Spending › Budget | T63: money | V63: 6
A64: F062 | B64: Not started | C64: Session 1 | D64: Needs | E64: Therapy (optional) | F64: Therapy or coaching | G64: Secondary | H64: Amount plus frequency (weekly, monthly, yearly, one-off) | I64: DRAFTT and FAT shares, Lean FI (FAT costs), estimate vs actual | J64: Every line: covered/shared options, my share or split by count, should-get-this, N/A | K64: Client | M64: All | N64: Medium | P64: Now | Q64: Optional DRAFTT line; Your comment: check whether health insurance reimburses; track reimbursed amount | S64: Spending › Budget | T64: money | V64: 6
A65: F063 | B65: Not started | C65: Session 1 | D65: Needs | E65: Health | F65: Out-of-pocket medical and prescriptions | G65: Secondary | H65: Amount plus frequency (weekly, monthly, yearly, one-off) | I65: DRAFTT and FAT shares, Lean FI (FAT costs), estimate vs actual | J65: Every line: covered/shared options, my share or split by count, should-get-this, N/A | K65: Client | M65: All | N65: Medium | P65: Now | S65: Spending › Budget | T65: money | V65: 6
A66: F064 | B66: Not started | C66: Session 1 | D66: Needs | E66: Phone and subscriptions | F66: Phone plan | G66: Secondary | H66: Amount plus frequency (weekly, monthly, yearly, one-off) | I66: DRAFTT and FAT shares, Lean FI (FAT costs), estimate vs actual | J66: Every line: covered/shared options, my share or split by count, should-get-this, N/A | K66: Client | M66: All | N66: Low | P66: Now | Q66: Family plan = small win; Your comment: covered? by who? or my share | S66: Spending › Budget | T66: money | V66: 6
A67: F065 | B67: Not started | C67: Session 2+ | D67: Needs | E67: Phone and subscriptions | F67: Subscriptions (list) | G67: Tertiary | H67: Amount plus frequency (weekly, monthly, yearly, one-off) | I67: DRAFTT and FAT shares, Lean FI (FAT costs), estimate vs actual | J67: Every line: covered/shared options, my share or split by count, should-get-this, N/A | K67: Client | M67: All | N67: Low | P67: Now | Q67: Batch small wins tab; Your comment: covered by who, my share, how many people split it | S67: Spending › Budget | T67: money | V67: 6
A68: F066 | B68: Not started | C68: Session 1 | D68: Needs | E68: Wants | F68: Wants bucket (one total) | G68: Primary | H68: Amount plus frequency (weekly, monthly, yearly, one-off) | I68: DRAFTT and FAT shares, Lean FI (FAT costs), estimate vs actual | J68: Every line: covered/shared options, my share or split by count, should-get-this, N/A | K68: Client | M68: All | N68: High | P68: Now | Q68: One bucket for now (no Need/Want tagging yet) | S68: Spending › Budget | T68: money | V68: 6
A69: F067 | B69: Not started | C69: Session 1 | D69: Needs | E69: Wants | F69: Travel | G69: Secondary | H69: Amount plus frequency (weekly, monthly, yearly, one-off) | I69: DRAFTT and FAT shares, Lean FI (FAT costs), estimate vs actual | J69: Every line: covered/shared options, my share or split by count, should-get-this, N/A | K69: Client | M69: All | N69: Medium | P69: Now | S69: Spending › Budget | T69: money | V69: 6
A70: F068 | B70: Not started | C70: Session 1 | D70: Needs | E70: Wants | F70: Gifts and giving | G70: Secondary | H70: Amount plus frequency (weekly, monthly, yearly, one-off) | I70: DRAFTT and FAT shares, Lean FI (FAT costs), estimate vs actual | J70: Every line: covered/shared options, my share or split by count, should-get-this, N/A | K70: Client | M70: All | N70: Low | P70: Now | S70: Spending › Budget | T70: money | V70: 6
A71: F069 | B71: Not started | C71: Session 1 | D71: Needs | E71: Wants | F71: Money sent to family | G71: Secondary | H71: Amount plus frequency (weekly, monthly, yearly, one-off) | I71: DRAFTT and FAT shares, Lean FI (FAT costs), estimate vs actual | J71: Every line: covered/shared options, my share or split by count, should-get-this, N/A | K71: Client | M71: All | N71: Medium | P71: Now | Q71: Support you give | S71: Spending › Budget | T71: money | V71: 6
A72: F070 | B72: Not started | C72: Session 1 | D72: Needs | E72: Kids | F72: Childcare and babysitting | G72: Secondary | H72: Amount plus frequency (weekly, monthly, yearly, one-off) | I72: DRAFTT and FAT shares, Lean FI (FAT costs), estimate vs actual | J72: Every line: covered/shared options, my share or split by count, should-get-this, N/A | K72: Client | M72: All | N72: High | P72: Now | Q72: Only if dependents; Your comment: if no dependents ignore; build out comprehensive | S72: Spending › Budget | T72: money | V72: 6
A73: F071 | B73: Not started | C73: Session 1 | D73: Needs | E73: Kids | F73: Diapers, formula, baby supplies | G73: Secondary | H73: Amount plus frequency (weekly, monthly, yearly, one-off) | I73: DRAFTT and FAT shares, Lean FI (FAT costs), estimate vs actual | J73: Every line: covered/shared options, my share or split by count, should-get-this, N/A | K73: Client | M73: All | N73: Medium | P73: Now | Q73: Only if dependents | S73: Spending › Budget | T73: money | V73: 6
A74: F072 | B74: Not started | C74: Session 1 | D74: Needs | E74: Kids | F74: Clothes and shoes | G74: Secondary | H74: Amount plus frequency (weekly, monthly, yearly, one-off) | I74: DRAFTT and FAT shares, Lean FI (FAT costs), estimate vs actual | J74: Every line: covered/shared options, my share or split by count, should-get-this, N/A | K74: Client | M74: All | N74: Medium | P74: Now | Q74: Only if dependents | S74: Spending › Budget | T74: money | V74: 6
A75: F073 | B75: Not started | C75: Session 1 | D75: Needs | E75: Kids | F75: School tuition and fees | G75: Secondary | H75: Amount plus frequency (weekly, monthly, yearly, one-off) | I75: DRAFTT and FAT shares, Lean FI (FAT costs), estimate vs actual | J75: Every line: covered/shared options, my share or split by count, should-get-this, N/A | K75: Client | M75: All | N75: High | P75: Now | Q75: Only if dependents | S75: Spending › Budget | T75: money | V75: 6
A76: F074 | B76: Not started | C76: Session 1 | D76: Needs | E76: Kids | F76: Activities, camps, lessons | G76: Secondary | H76: Amount plus frequency (weekly, monthly, yearly, one-off) | I76: DRAFTT and FAT shares, Lean FI (FAT costs), estimate vs actual | J76: Every line: covered/shared options, my share or split by count, should-get-this, N/A | K76: Client | M76: All | N76: Medium | P76: Now | Q76: Only if dependents | S76: Spending › Budget | T76: money | V76: 6
A77: F075 | B77: Not started | C77: Session 2+ | D77: Needs | E77: Kids | F77: Kids' medical and dental | G77: Tertiary | H77: Amount plus frequency (weekly, monthly, yearly, one-off) | I77: DRAFTT and FAT shares, Lean FI (FAT costs), estimate vs actual | J77: Every line: covered/shared options, my share or split by count, should-get-this, N/A | K77: Client | M77: All | N77: Medium | P77: Now | Q77: Only if dependents | S77: Spending › Budget | T77: money | V77: 6
A78: F076 | B78: Not started | C78: Session 2+ | D78: Needs | E78: Kids | F78: Toys, birthdays, school supplies | G78: Tertiary | H78: Amount plus frequency (weekly, monthly, yearly, one-off) | I78: DRAFTT and FAT shares, Lean FI (FAT costs), estimate vs actual | J78: Every line: covered/shared options, my share or split by count, should-get-this, N/A | K78: Client | M78: All | N78: Low | P78: Now | Q78: Only if dependents | S78: Spending › Budget | T78: money | V78: 6
A79: F077 | B79: Not started | C79: Session 2+ | D79: Needs | E79: Kids | F79: Allowance and phone | G79: Tertiary | H79: Amount plus frequency (weekly, monthly, yearly, one-off) | I79: DRAFTT and FAT shares, Lean FI (FAT costs), estimate vs actual | J79: Every line: covered/shared options, my share or split by count, should-get-this, N/A | K79: Client | M79: All | N79: Low | P79: Now | Q79: Only if dependents | S79: Spending › Budget | T79: money | V79: 6
A80: F078 | B80: Not started | C80: Session 2+ | D80: Needs | E80: Kids | F80: 529 or savings for kids | G80: Tertiary | H80: Amount plus frequency (weekly, monthly, yearly, one-off) | I80: DRAFTT and FAT shares, Lean FI (FAT costs), estimate vs actual | J80: Every line: covered/shared options, my share or split by count, should-get-this, N/A | K80: Client | M80: All | N80: Medium | P80: Now | Q80: Only if dependents. Links to Assets | S80: Spending › Budget | T80: money | V80: 6
A81: F079 | B81: Not started | C81: Session 1 | D81: Needs | E81: Pets | F81: Pet food | G81: Secondary | H81: Amount plus frequency (weekly, monthly, yearly, one-off) | I81: DRAFTT and FAT shares, Lean FI (FAT costs), estimate vs actual | J81: Every line: covered/shared options, my share or split by count, should-get-this, N/A | K81: Client | M81: All | N81: Medium | P81: Now | Q81: Only if they have pets; Your comment: comprehensive, include pet insurance, with split and covered | S81: Spending › Budget | T81: money | V81: 6
A82: F080 | B82: Not started | C82: Session 1 | D82: Needs | E82: Pets | F82: Vet visits and vaccines | G82: Secondary | H82: Amount plus frequency (weekly, monthly, yearly, one-off) | I82: DRAFTT and FAT shares, Lean FI (FAT costs), estimate vs actual | J82: Every line: covered/shared options, my share or split by count, should-get-this, N/A | K82: Client | M82: All | N82: Medium | P82: Now | Q82: Only if they have pets | S82: Spending › Budget | T82: money | V82: 6
... A87: F085 | B87: Not started | C87: Session 2+ | D87: Needs | E87: Pets | F87: Supplies, toys, litter | G87: Tertiary | H87: Amount plus frequency (weekly, monthly, yearly, one-off) | I87: DRAFTT and FAT shares, Lean FI (FAT costs), estimate vs actual | J87: Every line: covered/shared options, my share or split by count, should-get-this, N/A | K87: Client | M87: All | N87: Low | P87: Now | Q87: Only if they have pets | S87: Spending › Budget | T87: money | V87: 6
A88: F086 | B88: Not started | C88: Session 2+ | D88: Needs | E88: Other | F88: Education and courses | G88: Tertiary | H88: Amount plus frequency (weekly, monthly, yearly, one-off) | I88: DRAFTT and FAT shares, Lean FI (FAT costs), estimate vs actual | J88: Every line: covered/shared options, my share or split by count, should-get-this, N/A | K88: Client | M88: All | N88: Low | P88: Now | S88: Spending › Budget | T88: money | V88: 6
A89: F087 | B89: Not started | C89: Session 1 | D89: Needs | E89: Each line | F89: Who pays | G89: Secondary | H89: Pick: me, split, included in rent, covered by someone else, N/A | I89: Your comment: shared or covered options for everything | J89: Shows behind each line's caret | K89: Client | M89: All | N89: Medium | P89: Now | S89: Spending › Budget | T89: choice | U89: me, split, included in rent, covered by someone else, N/A | V89: 6
A90: F088 | B90: Not started | C90: Session 1 | D90: Needs | E90: Each line | F90: Covered by | G90: Secondary | H90: Pick: parents, partner, roommate, employer, insurance, other (name it) | I90: Tracks who supports the client | J90: Shows behind each line's caret | K90: Client | M90: All | N90: Medium | P90: Now | S90: Spending › Budget | T90: choice | U90: parents, partner, roommate, employer, insurance, other (name it) | V90: 6
A91: F089 | B91: Not started | C91: Session 1 | D91: Needs | E91: Each line | F91: Amount they cover | G91: Secondary | H91: Amount or % | I91: Tracks how much someone else is supporting; total shown on Report | J91: Shows behind each line's caret | K91: Client | M91: All | N91: Medium | P91: Now | S91: Spending › Budget | T91: money | V91: 6
A92: F090 | B92: Not started | C92: Session 1 | D92: Needs | E92: Each line | F92: Split by how many | G92: Secondary | H92: Stepper, defaults to roommate count | I92: Your comment: based on how many roommates | J92: Shows behind each line's caret | K92: Client | M92: All | N92: Medium | P92: Now | S92: Spending › Budget | T92: whole number | V92: 6
A93: F091 | B93: Not started | C93: Session 1 | D93: Needs | E93: Each line | F93: Or just my share | G93: Secondary | H93: Amount | I93: Your comment: sometimes you just say here's what I pay | J93: Shows behind each line's caret | K93: Client | M93: All | N93: Medium | P93: Now | S93: Spending › Budget | T93: money | V93: 6
A94: F092 | B94: Not started | C94: Session 1 | D94: Needs | E94: Each line | F94: Should have, don't yet | G94: Secondary | H94: Button | I94: Gap to fill (renters insurance, emergency fund); goes on the to-do list | J94: Shows behind each line's caret | K94: Client | M94: All | N94: Medium | P94: Now | S94: Spending › Budget | T94: text | V94: 6
A95: F093 | B95: Not started | C95: Session 2+ | D95: Needs | E95: Each line | F95: Reimbursed amount | G95: Tertiary | H95: Amount | I95: Therapy, medical, work costs that come back | J95: Shows behind each line's caret | K95: Client | M95: All | N95: Medium | P95: Now | S95: Spending › Budget | T95: money | V95: 6
A96: F094 | B96: Not started | C96: Session 1 | D96: Needs | E96: Support received | F96: Total support from others | G96: Secondary | H96: Computed | I96: How much of the budget others cover (parents, partner). Matters if it stops | K96: Computed | M96: Computed | N96: High | P96: Now | S96: Spending › Budget | T96: computed | V96: 6
A97: F095 | B97: Not started | C97: Session 1 | D97: Needs | E97: Car gate | F97: Has a car | G97: Primary | H97: Yes or no (from Profile or Assets) | I97: Car-only lines appear only with a car | K97: Client | M97: Know it | N97: High | P97: Now | S97: Spending › Budget | T97: choice | U97: Yes, No, Not sure | V97: 6
A98: F096 | B98: Not started | C98: Session 1 | D98: Needs | E98: Pets gate | F98: Has pets (how many) | G98: Secondary | H98: Stepper | I98: Pet lines appear only with pets | K98: Client | M98: Know it | N98: Medium | P98: Now | S98: Spending › Budget | T98: whole number | V98: 6
A99: F097 | B99: Not started | C99: Session 1 | D99: Needs | E99: Each line | F99: Frequency | G99: Secondary | H99: Pick one: weekly, monthly, yearly, one-off | I99: Annual costs shown monthly | K99: Client | M99: All | N99: Medium | P99: Now | S99: Spending › Budget | T99: choice | U99: weekly, monthly, yearly, one-off | V99: 6
A100: F098 | B100: Not started | C100: Monthly | D100: Needs | E100: Each line | F100: Actual amount (from cash flow log) | G100: Secondary | H100: Computed with gaps added | I100: Estimated vs actual, biggest culprits | K100: Computed | M100: Computed | N100: High | P100: Now | S100: Spending › Budget | T100: computed | V100: 6
A101: F099 | B101: Not started | C101: Session 2+ | D101: Needs | E101: Each line | F101: Happiness rating | G101: Tertiary | H101: 1 to 5 stars | I101: Joy per dollar, share of total joy | K101: Client | M101: All | N101: Medium | P101: Now | S101: Spending › Budget | T101: text | V101: 6
A102: F100 | B102: Not started | C102: Later | D102: Needs | E102: Each line | F102: Need or want tag | G102: Tertiary | H102: Toggle | I102: Parked for a later pass (Oct 28) | K102: Client | M102: All | N102: Medium | P102: Later | S102: Spending › Budget | T102: choice | V102: 6
A103: F101 | B103: Not started | C103: Later | D103: Needs | E103: Each line | F103: Unavoidable or mistake tag | G103: Tertiary | H103: Toggle | I103: Shows what mistakes cost and whether they repeat | K103: Client | M103: All | N103: Low | P103: Later | S103: Spending › Budget | T103: choice | V103: 6
A104: F102 | B104: Not started | C104: Later | D104: Needs | E104: Each line | F104: Whose value is this | G104: Tertiary | H104: Tag: me, partner, family, other | I104: What Matters priorities | K104: Client | M104: All | N104: Low | P104: Later | S104: Spending › Budget | T104: choice | U104: me, partner, family, other | V104: 6
...

Sheet Feature details
A1: SLAM features: what each one does and what it reads
A2: ID | B2: Build status | C2: Category | D2: Feature | E2: What it does | F2: Layer | G2: Scope | H2: Reads fields from | I2: Notes / references
A3: X001 | B3: Not started | C3: Entry | D3: Gate checklist | E3: Which of these do you have today. Unchecked areas never appear | F3: Primary | G3: Now | H3: Profile | I3: ProjectionLab
A4: X002 | B4: Not started | C4: Entry | D4: Count first, then rows | E4: How many of each type, then one row each, add or duplicate | F4: Primary | G4: Now | H4: Debt, Assets | I4: Oct 28 decision
A5: X003 | B5: Not started | C5: Entry | D5: Add picker with search | E5: Grouped types with counts plus a search bar | F5: Primary | G5: Now | H5: All multi-item areas | I5: ProjectionLab
A6: X004 | B6: Not started | C6: Entry | D6: Carets for depth | E6: Primary fields show, Secondary and Tertiary behind a caret | F6: Primary | G6: Now | H6: All | I6: Your sheet row 8
A7: X005 | B7: Not started | C7: Entry | D7: Type-a-little-and-pick | E7: Flight-search style on every field | F7: Primary | G7: Now | H7: All
A8: X006 | B8: Not started | C8: Entry | D8: 'Per' picker | E8: Enter any amount per paycheck, month or year | F8: Primary | G8: Now | H8: Income, Needs
A9: X007 | B9: Not started | C9: Entry | D9: Solve the other | E9: Enter gross, take-home or both; app solves the rest and marks it Computed | F9: Primary | G9: Now | H9: Income
A10: X008 | B10: Not started | C10: Entry | D10: 'I'm not / I don't' on every question | E10: Built-in none answer so a section can be complete with nothing in it | F10: Primary | G10: Now | H10: All
A11: X009 | B11: Not started | C11: Entry | D11: Blank defaults | E11: New rows start blank, not 0% and $0 | F11: Primary | G11: Now | H11: All | I11: ProjectionLab shows 0 years to pay off before anything is entered
A12: X010 | B12: Not started | C12: Entry | D12: Owner on every row | E12: Solo, partner or joint | F12: Primary | G12: Now | H12: All | I12: Couples support
A13: X011 | B13: Not started | C13: Entry | D13: Fast Track (a mode, started by a button) | E13: 80/20 quick setup in about 5 minutes; walks the Basics pass across Numbers tabs | F13: Primary | G13: Now | H13: Fast Track stage
A14: X012 | B14: Not started | C14: Entry | D14: Guide me mode | E14: Session path on Numbers, not its own tab | F14: Primary | G14: Now | H14: Session 1 stage
A15: X013 | B15: Not started | C15: Entry | D15: One page mode (Express form) | E15: By section | One page toggle on Numbers: every question on one page | F15: Secondary | G15: Now
A16: X014 | B16: Not started | C16: Entry | D16: Undo and redo | E16: Global | F16: Secondary | G16: Now
A17: X015 | B17: Not started | C17: Status and tags | D17: Confidence status per number | E17: Know it, roughly, not sure, will email, not now, not for me, computed | F17: Primary | G17: Now | H17: All | I17: Status process needs redoing (Oct 27)
A18: X016 | B18: Not started | C18: Status and tags | D18: Homework from 'will email' | E18: Any number marked will email lands on the homework list | F18: Primary | G18: Now | H18: All
A19: X017 | B19: Not started | C19: Status and tags | D19: Rough and stale nag | E19: Age of every number plus next check date | F19: Primary | G19: Now | H19: All
A20: X018 | B20: Not started | C20: Status and tags | D20: Revisit list | E20: One place listing every rough or not sure number | F20: Primary | G20: Now | H20: All
A21: X019 | B21: Not started | C21: Status and tags | D21: Stress rating | E21: 1 to 5 on debts and accounts, feeds payoff order | F21: Primary | G21: Now | H21: Debt, Assets
A22: X020 | B22: Not started | C22: Status and tags | D22: Materiality | E22: Under $100/yr is trivial; real hourly wage per hour of effort is the material line | F22: Secondary | G22: Now
A23: X021 | B23: Not started | C23: Status and tags | D23: Next 3 numbers | E23: Ranked by leverage on FI date and metrics, one big, two small | F23: Primary | G23: Now | H23: All
A24: X022 | B24: Not started | C24: Status and tags | D24: Completion bars | E24: Two bars per section and topic (core, full detail) with a clickable what's next | F24: Primary | G24: Now | H24: All
A25: X023 | B25: Not started | C25: Status and tags | D25: Small wins tab | E25: Batch the trivial items as quick mini-games | F25: Secondary | G25: Later
A26: X024 | B26: Not started | C26: Engine | D26: Year-by-year projection | E26: One continuous engine, now through death, all tools read from it | F26: Primary | G26: Now
A27: X025 | B27: Not started | C27: Engine | D27: Federal plus FICA taxes | E27: v1 tax depth | F27: Primary | G27: Now
A28: X026 | B28: Not started | C28: Engine | D28: Savings waterfall to limits | E28: Match, then IRA, HSA, 401(k) to the legal limit, with a selectable goal | F28: Secondary | G28: Now
A29: X027 | B29: Not started | C29: Engine | D29: Debt payoff simulation | E29: Months, date, total interest, avalanche, snowball, stress-weighted | F29: Primary | G29: Now
A30: X028 | B30: Not started | C30: Engine | D30: Triple D pace | E30: Optimistic, likely, pessimistic bands | F30: Secondary | G30: Now
A31: X029 | B31: Not started | C31: Engine | D31: Real dollars default | E31: Nominal toggle with a plain definition | F31: Tertiary | G31: Now
A32: X030 | B32: Not started | C32: Engine | D32: Advanced toggles | E32: Roth ladder, 72(t), rule of 55, ACA tradeoff | F32: Tertiary | G32: Later
A33: X031 | B33: Not started | C33: Metrics | D33: Net worth (liquid and total) | E33: Unlocks once its inputs exist | F33: Primary | G33: Now
A34: X032 | B34: Not started | C34: Metrics | D34: Savings rate | E34: Unlocks once its inputs exist | F34: Primary | G34: Now
A35: X033 | B35: Not started | C35: Metrics | D35: DRAFTT proportions | E35: Unlocks once its inputs exist | F35: Primary | G35: Now
A36: X034 | B36: Not started | C36: Metrics | D36: FI date and FI number | E36: Unlocks once its inputs exist | F36: Primary | G36: Now
... A44: X042 | B44: Not started | C44: Metrics | D44: Metrics unlocked shelf | E44: Like rewards unlocked, but metrics | F44: Secondary | G44: Now
A45: X043 | B45: Not started | C45: Visuals | D45: Net worth donuts | E45: Net worth, assets, liabilities, equity with tabs underneath | F45: Primary | G45: Now | I45: ProjectionLab Current Finances
A46: X044 | B46: Not started | C46: Visuals | D46: Cash flow Sankey | E46: Income to spending to saving | F46: Primary | G46: Now
A47: X045 | B47: Not started | C47: Visuals | D47: FI timeline with milestones | E47: Drag-to-see-the-future slider | F47: Secondary | G47: Now
A48: X046 | B48: Not started | C48: Visuals | D48: Debt payoff chart | E48: Balance over time per debt | F48: Secondary | G48: Now
A49: X047 | B49: Not started | C49: Visuals | D49: Graceful degradation | E49: Months at full spending, DRAFTT, FAT, food and housing only | F49: Secondary | G49: Later
A50: X048 | B50: Not started | C50: Visuals | D50: Life Pyramid lens | E50: Maslow pyramid as a bar graph | F50: Tertiary | G50: Later
A51: X049 | B51: Not started | C51: Visuals | D51: Pareto of transactions | E51: Which few transactions make most spending | F51: Tertiary | G51: Later
A52: X050 | B52: Not started | C52: Visuals | D52: Year in review (Wrapped) | E52: After a year of month-end closes | F52: Tertiary | G52: Later
A53: X051 | B53: Not started | C53: Session workflow | D53: Discovery table | E53: Numbers from the sales call populate the map | F53: Primary | G53: Now
A54: X052 | B54: Not started | C54: Session workflow | D54: Session 1 curriculum | E54: About an hour, ordered questions, flexes when a client goes deeper | F54: Primary | G54: Now
A55: X053 | B55: Not started | C55: Session workflow | D55: Home agenda | E55: Home opens on today's agenda plus a one-sentence money summary | F55: Primary | G55: Now
A56: X054 | B56: Not started | C56: Session workflow | D56: FI date reveal | E56: Big but calm reveal at end of call | F56: Primary | G56: Now
A57: X055 | B57: Not started | C57: Session workflow | D57: One-pager | E57: Key stats, to-dos, goals, strengths, struggles, do more, do less | F57: Primary | G57: Now
... A80: X078 | B80: Not started | C80: Data | D80: Client view and comments | E80: Shared coach and client view | F80: Tertiary | G80: Later
A81: X079 | B81: Not started | C81: Parked | D81: Document readers (paystub, 1040) | F81: Tertiary | G81: Parked
A82: X080 | B82: Not started | C82: Parked | D82: Secret wants features (permission to spend, stop-sprinting alert, two-player mode, rehearsal mode) | F82: Tertiary | G82: Parked
A83: X081 | B83: Not started | C83: Parked | D83: Next stage, Eras, dream life | F83: Tertiary | G83: Parked
A84: X082 | B84: Not started | C84: Parked | D84: Curation layer (podcasts, reading) | F84: Tertiary | G84: Parked
A85: X083 | B85: Not started | C85: Parked | D85: Communal money date | F85: Tertiary | G85: Parked
A86: X084 | B86: Not started | C86: Parked | D86: Hamilton or Dante theming | F86: Tertiary | G86: Parked
A87: X085 | B87: Not started | C87: Added after review | D87: Bulk select | E87: Checkbox per row and Select all; slim bar with duplicate, delete, reset, set status, link to card | F87: Primary | G87: Now
A88: X086 | B88: Not started | C88: Added after review | D88: Link bills to a card in one step | E88: Card buttons (4 or fewer cards) from the bulk bar or More ▸ › Paid with on the row | F88: Secondary | G88: Now
A89: X087 | B89: Not started | C89: Added after review | D89: Row actions as small icons | E89: Duplicate ⧉, reset ↺, delete 🗑 (undo toast) on every multi-item row | F89: Primary | G89: Now
A90: X088 | B90: Not started | C90: Added after review | D90: Section reset | E90: Clear a whole section after a confirm | F90: Secondary | G90: Now
A91: X089 | B91: Not started | C91: Added after review | D91: Reset client | E91: Clear everything after typing the client's name | F91: Secondary | G91: Now
A92: X090 | B92: Not started | C92: Added after review | D92: Calendar month grid | E92: Day cells with income, bill, maybe and win chips plus an end-of-day running balance | F92: Primary | G92: Now
A93: X091 | B93: Not started | C93: Added after review | D93: Calendar entries | E93: Name, amount, in/out/maybe, date, repeats; links to budget line, account and debt | F93: Primary | G93: Now
A94: X092 | B94: Not started | C94: Added after review | D94: Low balance warning | E94: Flags days below a balance you set | F94: Secondary | G94: Now
A95: X093 | B95: Not started | C95: Added after review | D95: Auto due dates | E95: Card and loan due days appear on the calendar | F95: Secondary | G95: Now
A96: X094 | B96: Not started | C96: Added after review | D96: Drag to reschedule | E96: Move a chip to another day | F96: Secondary | G96: Now
A97: X095 | B97: Not started | C97: Added after review | D97: Got it / Paid | E97: Planned or maybe becomes actual on the real date | F97: Tertiary | G97: Now
A98: X096 | B98: Not started | C98: Added after review | D98: Wins on the calendar | E98: Milestones, payoffs, raises as dated chips | F98: Tertiary | G98: Now
... A122: X120 | B122: Not started | C122: Added after review | D122: Disclaimer | E122: On one-pager and pre-call form | F122: Secondary | G122: Now

Sheet Tags and layers
A1: What every tag means
A2: Tag | B2: Value | C2: Meaning
A3: Layer | B3: Primary | C3: Shows on the first line of the row. Needed for the core metrics
A4: Layer | B4: Secondary | C4: Behind the caret. Asked in session 1 if time allows
A5: Layer | B5: Tertiary | C5: Deep detail. Session 2+ or homework
A6: Stage | B6: Pre-call | C6: Client fills before the onboarding call (tap only)
A7: Stage | B7: Discovery | C7: Sales call numbers
A8: Stage | B8: Fast Track | C8: The 5-minute core: enough for net worth, savings rate and an FI date
A9: Stage | B9: Session 1 | C9: Worked through together, you driving
A10: Stage | B10: Session 2+ | C10: Later sessions or deeper passes
A11: Stage | B11: Monthly | C11: Money date and month-end close
A12: Stage | B12: Computed | C12: Never asked; the app works it out
A13: Stage | B13: Later / Parked | C13: Not in the current build
... A29: Build status | B29: Not started / Spec'd / Built / Tested | C29: Where it stands in SLAM

Sheet Demo client
A1: Demo client (made up, safe for the public repo)
A3: Age | B3: 29
A4: Monthly take-home | B4: 4800
A5: Monthly spending, all in | B5: 3600
A6: Rent (my share) | B6: 1650
A7: Utilities | B7: 120
A8: Cash savings | B8: 6000
A9: Invested (all accounts) | B9: 22000
A10: Car value | B10: 9500
A11: Car loan balance | B11: 7000
A12: Car loan APR | B12: 0.0714
A13: Car loan payment / mo | B13: 320
A14: Student loan balance | B14: 18000
... A21: Withdrawal rate | B21: 0.04
A23: EXPECTED OUTPUTS
A24: Total net worth (M40) | B24: =B8+B9+B10-B11-B14-B17
A25: Liquid cash runway, months (M42) | B25: =B8/B5
A26: Monthly surplus (M27) | B26: =B4-B5
A27: Savings rate (M28) | B27: =(B4-B5)/B4
A28: Housing % of take-home (M2A) | B28: =(B6+B7)/B4
A29: Credit card payoff months (M31) | B29: =ROUNDUP(NPER(B18/12,-B19,B17),0)
A30: Credit card total interest (M32) | B30: =NPER(B18/12,-B19,B17)*B19-B17
A31: Student loan payoff months (M31) | B31: =ROUNDUP(NPER(B15/12,-B16,B14),0)
A32: Car loan payoff months (M31) | B32: =ROUNDUP(NPER(B12/12,-B13,B11),0)
A33: Rule of 5 target $ (M43) | B33: =B3/5*B5
A34: Rule of 5 keep-pace add / mo (M43) | B34: =B5/60
A35: FI number (M50) | B35: =B5*12/B21
A36: Months to FI, surplus fully invested (M53) | B36: =ROUNDUP(NPER((1+B20)^(1/12)-1,-(B4-B5),-B9,B5*12/B21),0)
A37: Coast FI number today, retire at 60 (M54) | B37: =B5*12/B21/(1+B20)^(60-B3)

Sheet Open questions
A1: Still to decide
A2: # | B2: Question | C2: Your answer
A3: 1 | B3: Return presets before or after inflation? | C3: After inflation. 12% is the hopeful no-inflation case (Oct 28)
A4: 2 | B4: Guess vs Roughly: keep both or merge? | C4: Keep both (Oct 28)
A5: 3 | B5: Budget grouping: DRAFTT letters or plain categories with a tag? | C5: Plain categories with a DRAFTT tag, so degradation can be measured (Oct 28)
A6: 4 | B6: Main tab names | C6: Renamed: Home, My Money, Spending, Plan, Report (Oct 28). Change here if you prefer other words
A7: 5 | B7: Statement upload format | C7: Both CSV and PDF (phase 4) (Oct 28)
A8: 6 | B8: Test client: monthly take-home for the new job and all-in monthly spending (two yellow cells in the private file)
A9: 7 | B9: Test client: are the $20,000 student loan and credit card real? | C9: Roughly (Oct 28)
A10: 8 | B10: Rule of 5 keep-pace add = monthly spending / 60? | C10: Yes (Oct 28)
A11: 9 | B11: Typical rates from the Federal Reserve? | C11: Yes; G.19 Q2 2026 used (Oct 28)
